Workbook
Name Slicer_product_category: #N/A
Name Slicer_year: #N/A

Sheet Return Rate 2
A3: Row Labels | B3: Sum of returned | C3: Sum of final_order | D3: Sum of Return Rate
A4: Beauty | B4: 83 | C4: 472 | D4: 0.17584746
A5: Books | B5: 76 | C5: 446 | D5: 0.17040359
A6: Clothing | B6: 88 | C6: 507 | D6: 0.17357002
A7: Electronics | B7: 96 | C7: 474 | D7: 0.20253165
A8: Furniture | B8: 79 | C8: 465 | D8: 0.16989247
A9: Groceries | B9: 95 | C9: 471 | D9: 0.20169851
A10: Sports | B10: 95 | C10: 508 | D10: 0.18700787
A11: Grand Total | B11: 612 | C11: 3343 | D11: 0.1830691

Sheet Return Rate 2 (2)
A3: Row Labels | B3: Rata-rata Kepuasan | C3: Jumlah Rating
A4: Cancelled | B4: 2.9230769 | C4: 325
A5: Delivered | B5: 3.1306432 | C5: 2503
A6: Pending | B6: 3.0935673 | C6: 171
A7: Returned | B7: 2.4601449 | C7: 552
A8: Shipped | B8: 3.1617162 | C8: 303
A9: Grand Total | B9: 3.0179035 | C9: 3854

Sheet Nilai Retur
A1: order_status_clean | B1: Returned
A2: sales_flag | B2: Include
A4: Row Labels | B4: Sum of sales_amount
A5: Electronics | B5: 20029868
A6: Furniture | B6: 6970993.6
A7: Sports | B7: 3534929.9
A8: Clothing | B8: 873313.81
A9: Beauty | B9: 499254.57
A10: Books | B10: 340159.07
A11: Groceries | B11: 146963.62
A12: Grand Total | B12: 32395483

Sheet P6 Return
A3: Row Labels | B3: Sum of returned | C3: Sum of final_order | D3: Return Rate
A4: Electronics | B4: 96 | C4: 474 | D4: 0.20253165
A5: Groceries | B5: 95 | C5: 471 | D5: 0.20169851
A6: Sports | B6: 95 | C6: 508 | D6: 0.18700787
A7: Beauty | B7: 83 | C7: 472 | D7: 0.17584746
A8: Clothing | B8: 88 | C8: 507 | D8: 0.17357002
A9: Books | B9: 76 | C9: 446 | D9: 0.17040359
A10: Furniture | B10: 79 | C10: 465 | D10: 0.16989247
A11: Grand Total | B11: 612 | C11: 3343 | D11: 0.1830691

Sheet P6 Return (2)
A3: Row Labels | B3: Return Rate
A4: Electronics | B4: 0.20253165
A5: Groceries | B5: 0.20169851
A6: Sports | B6: 0.18700787
A7: Beauty | B7: 0.17584746
A8: Clothing | B8: 0.17357002
A9: Books | B9: 0.17040359
A10: Furniture | B10: 0.16989247
A11: Grand Total | B11: 0.1830691

Sheet Cleaned-retail-sales-dataset
A1: order_id | B1: order_date | C1: order_date_clean | D1: customer_id | E1: customer_name | F1: age | G1: age_clean | H1: gender | I1: gender (clean) | J1: region | K1: city | L1: product_category | M1: product_name | N1: quantity | O1: quantity_clean | P1: unit_price | Q1: discount_pct | R1: sales_amount | S1: profit | T1: profit_margin | U1: shipping_cost | V1: payment_method | W1: customer_satisfaction | X1: return_flag | Y1: order_status | Z1: order_status_clean | AA1: days_clean | AB1: days_to_ship | AC1: year | AD1: year_month | AE1: age_group | AF1: discount_band | AG1: sales_flag | AH1: returned | AI1: final_order | AJ1: cancelled | AK1: orders_count
A2: ORD-04199 | B2: 45656 | C2: 45656 | D2: CUST53723 | E2: Sunita Kumar | F2: 15 | G2: 15 | H2: Male | I2: Male | J2: North | K2: Chandigarh | L2: Beauty | M2: Face Cream | N2: 9 | O2: 9 | P2: 1820.1 | Q2: 0.28 | R2: 9661.83 | S2: 5675.66 | T2: 0.587 | U2: 46.9 | V2: EMI | W2: 2 | X2: TRUE | Y2: Returned | Z2: Returned | AA2: 3 | AB2: 3 | AC2: 2024 | AD2: 45627 | AE2: <18 | AF2: 21-30% | AG2: =IF(N2=999,"Exclude","Include") -> Include | AH2: =IF(Z2="Returned",1,0) -> 1 | AI2: =IF(OR(Z2="Delivered",Z2="Returned"),1,0) -> 1 | AJ2: =IF(Z2="Cancelled",1,0) -> 0 | AK2: =1 -> 1
A3: ORD-04200 | B3: 45656 | C3: 45656 | D3: CUST38440 | E3: Rohan Rao | F3: 22 | G3: 22 | H3: Other | I3: Other | J3: South | K3: Bangalore | L3: Furniture | M3: Sofa | N3: 6 | O3: 6 | P3: 5868.58 | Q3: 0.29 | R3: 27272.26 | S3: 8506.96 | T3: 0.312 | U3: 61.17 | V3: Cash on Delivery | W3: 3 | X3: TRUE | Y3: Returned | Z3: Returned | AA3: 5 | AB3: 5 | AC3: 2024 | AD3: 45627 | AE3: 18-25 | AF3: 21-30% | AG3: =IF(N3=999,"Exclude","Include") -> Include | AH3: =IF(Z3="Returned",1,0) -> 1 | AI3: =IF(OR(Z3="Delivered",Z3="Returned"),1,0) -> 1 | AJ3: =IF(Z3="Cancelled",1,0) -> 0 | AK3: =1 -> 1
A4: ORD-04198 | B4: 45655 | C4: 45655 | D4: CUST54617 | E4: Kavya Joshi | F4: 36 | G4: 36 | H4: Other | I4: Other | J4: East | K4: Patna | L4: Furniture | M4: Chair | N4: 6 | O4: 6 | P4: 21398.46 | Q4: 0.34 | R4: 75488.55 | S4: 18648.21 | T4: 0.247 | U4: 99.52 | V4: EMI | W4: 4 | X4: FALSE | Y4: Delivered | Z4: Delivered | AA4: 1 | AB4: 1 | AC4: 2024 | AD4: 45627 | AE4: 36-45 | AF4: 31-40% | AG4: =IF(N4=999,"Exclude","Include") -> Include | AH4: =IF(Z4="Returned",1,0) -> 0 | AI4: =IF(OR(Z4="Delivered",Z4="Returned"),1,0) -> 1 | AJ4: =IF(Z4="Cancelled",1,0) -> 0 | AK4: =1 -> 1
A5: ORD-04195 | B5: 45654 | C5: 45654 | D5: CUST13220 | E5: Ritu Gupta | F5: 36 | G5: 36 | H5: Other | I5: Other | J5: East | K5: Bhubaneswar | L5: Furniture | M5: Desk | N5: 9 | O5: 9 | P5: 21875.15 | Q5: 0.01 | R5: 161990.01 | S5: 51700.42 | T5: 0.319 | U5: 87.08 | V5: Credit Card | W5: 4 | X5: FALSE | Y5: Delivered | Z5: Delivered | AA5: 10 | AB5: 10 | AC5: 2024 | AD5: 45627 | AE5: 36-45 | AF5: 1-10% | AG5: =IF(N5=999,"Exclude","Include") -> Include | AH5: =IF(Z5="Returned",1,0) -> 0 | AI5: =IF(OR(Z5="Delivered",Z5="Returned"),1,0) -> 1 | AJ5: =IF(Z5="Cancelled",1,0) -> 0 | AK5: =1 -> 1
A6: ORD-04196 | B6: 45654 | C6: 45654 | D6: CUST70995 | E6: Rahul Gupta | F6: 40 | G6: 40 | H6: Male | I6: Male | J6: North | K6: Ludhiana | L6: Electronics | M6: Headphones | N6: 5 | O6: 5 | P6: 8516.83 | Q6: 0.34 | R6: 25126 | S6: 3420.94 | T6: 0.136 | U6: 56.78 | V6: UPI | W6: 4 | X6: FALSE | Y6: Delivered | Z6: Delivered | AA6: 4 | AB6: 4 | AC6: 2024 | AD6: 45627 | AE6: 36-45 | AF6: 31-40% | AG6: =IF(N6=999,"Exclude","Include") -> Include | AH6: =IF(Z6="Returned",1,0) -> 0 | AI6: =IF(OR(Z6="Delivered",Z6="Returned"),1,0) -> 1 | AJ6: =IF(Z6="Cancelled",1,0) -> 0 | AK6: =1 -> 1
A7: ORD-04197 | B7: December 28, 2024 | C7: 45654 | D7: CUST98908 | E7: Rohan Sharma | F7: 33 | G7: 33 | H7: Female | I7: Female | J7: West | K7: Mumbai | L7: Groceries | M7: Sugar | N7: 1 | O7: 1 | P7: 51.21 | Q7: 0.14 | R7: 42.95 | S7: 2.98 | T7: 0.069 | U7: 49.87 | V7: EMI | W7: 4 | X7: FALSE | Y7: Pending | Z7: Pending | AA7: 8 | AB7: 8 | AC7: 2024 | AD7: 45627 | AE7: 26-35 | AF7: 11-20% | AG7: =IF(N7=999,"Exclude","Include") -> Include | AH7: =IF(Z7="Returned",1,0) -> 0 | AI7: =IF(OR(Z7="Delivered",Z7="Returned"),1,0) -> 0 | AJ7: =IF(Z7="Cancelled",1,0) -> 0 | AK7: =1 -> 1
A8: ORD-04193 | B8: 45654 | C8: 45654 | D8: CUST18192 | E8: Nikhil Bose | F8: 25 | G8: 25 | H8: F | I8: Female | J8: East | K8: Patna | L8: Beauty | M8: Perfume | N8: 5 | O8: 5 | P8: 724.63 | Q8: 0.1 | R8: 3163.89 | S8: 1918.69 | T8: 0.606 | U8: 48.49 | V8: Credit Card | W8: 5 | X8: FALSE | Y8: Delivered | Z8: Delivered | AA8: 6 | AB8: 6 | AC8: 2024 | AD8: 45627 | AE8: 18-25 | AF8: 1-10% | AG8: =IF(N8=999,"Exclude","Include") -> Include | AH8: =IF(Z8="Returned",1,0) -> 0 | AI8: =IF(OR(Z8="Delivered",Z8="Returned"),1,0) -> 1 | AJ8: =IF(Z8="Cancelled",1,0) -> 0 | AK8: =1 -> 1
A9: ORD-04194 | B9: 45654 | C9: 45654 | D9: CUST18508 | E9: Sunita Sharma | F9: 56 | G9: 56 | H9: Male | I9: Male | J9: North | K9: Ludhiana | L9: Books | M9: Biography | N9: 2 | O9: 2 | P9: 709.51 | Q9: 0.08 | R9: 1228.87 | S9: 481.53 | T9: 0.392 | U9: 18.48 | V9: Net Banking | W9: 5 | X9: FALSE | Y9: Cancelled | Z9: Cancelled | AA9: 5 | AB9: 5 | AC9: 2024 | AD9: 45627 | AE9: 46-60 | AF9: 1-10% | AG9: =IF(N9=999,"Exclude","Include") -> Include | AH9: =IF(Z9="Returned",1,0) -> 0 | AI9: =IF(OR(Z9="Delivered",Z9="Returned"),1,0) -> 0 | AJ9: =IF(Z9="Cancelled",1,0) -> 1 | AK9: =1 -> 1
A10: ORD-04192 | B10: 45653 | C10: 45653 | D10: CUST70453 | E10: Shreya Shah | F10: 33 | G10: 33 | H10: m | I10: Male | J10: North | K10: Amritsar | L10: Books | M10: Fiction Novel | P10: 616.57 | Q10: 0.36 | R10: 344.18 | S10: 145.51 | T10: 0.423 | U10: 35.22 | V10: UPI | W10: 4 | X10: FALSE | Y10: Pending | Z10: Pending | AC10: 2024 | AD10: 45627 | AE10: 26-35 | AF10: 31-40% | AG10: =IF(N10=999,"Exclude","Include") -> Include | AH10: =IF(Z10="Returned",1,0) -> 0 | AI10: =IF(OR(Z10="Delivered",Z10="Returned"),1,0) -> 0 | AJ10: =IF(Z10="Cancelled",1,0) -> 0 | AK10: =1 -> 1
A11: ORD-04190 | B11: 45652 | C11: 45652 | D11: CUST01943 | E11: Amit Reddy | F11: 21 | G11: 21 | H11: Other | I11: Other | J11: North | K11: Ludhiana | L11: Sports | M11: Cricket Bat | N11: 6 | O11: 6 | P11: 5492.54 | Q11: 0.09 | R11: 25243.43 | S11: 6104.49 | T11: 0.242 | U11: 71.5 | V11: EMI | W11: 5 | X11: FALSE | Y11: Delivered | Z11: Delivered | AA11: 1 | AB11: 1 | AC11: 2024 | AD11: 45627 | AE11: 18-25 | AF11: 1-10% | AG11: =IF(N11=999,"Exclude","Include") -> Include | AH11: =IF(Z11="Returned",1,0) -> 0 | AI11: =IF(OR(Z11="Delivered",Z11="Returned"),1,0) -> 1 | AJ11: =IF(Z11="Cancelled",1,0) -> 0 | AK11: =1 -> 1
A12: ORD-04188 | B12: 45652 | C12: 45652 | D12: CUST03222 | E12: Pooja Bhat | H12: Other | I12: Other | J12: Central | K12: Bhopal | L12: Furniture | M12: Chair | N12: 10 | O12: 10 | P12: 21965.61 | Q12: 0.25 | R12: 142471.68 | S12: 51299.09 | T12: 0.36 | U12: 54.26 | V12: Net Banking | W12: 1 | X12: TRUE | Y12: Returned | Z12: Returned | AA12: 10 | AB12: 10 | AC12: 2024 | AD12: 45627 | AE12: Unknown | AF12: 21-30% | AG12: =IF(N12=999,"Exclude","Include") -> Include | AH12: =IF(Z12="Returned",1,0) -> 1 | AI12: =IF(OR(Z12="Delivered",Z12="Returned"),1,0) -> 1 | AJ12: =IF(Z12="Cancelled",1,0) -> 0 | AK12: =1 -> 1
A13: ORD-04191 | B13: 45652 | C13: 45652 | D13: CUST42768 | E13: Nisha Singh | F13: 4 | G13: 4 | H13: Female | I13: Female | J13: West | K13: Surat | L13: Sports | M13: Cycle | N13: 8 | O13: 8 | P13: 1646.28 | Q13: 0.25 | R13: 7889.98 | S13: 1643.93 | T13: 0.208 | U13: 58.56 | V13: Cash on Delivery | W13: 4 | X13: FALSE | Y13: Delivered | Z13: Delivered | AA13: 10 | AB13: 10 | AC13: 2024 | AD13: 45627 | AE13: <18 | AF13: 21-30% | AG13: =IF(N13=999,"Exclude","Include") -> Include | AH13: =IF(Z13="Returned",1,0) -> 0 | AI13: =IF(OR(Z13="Delivered",Z13="Returned"),1,0) -> 1 | AJ13: =IF(Z13="Cancelled",1,0) -> 0 | AK13: =1 -> 1
A14: ORD-04189 | B14: 45652 | C14: 45652 | D14: CUST28178 | E14: Sanjay Rao | F14: 32 | G14: 32 | H14: Other | I14: Other | J14: West | K14: Mumbai | L14: Electronics | M14: Smartwatch | N14: 4 | O14: 4 | P14: 64608.94 | Q14: 0.17 | R14: 191352.59 | S14: 27372.68 | T14: 0.143 | U14: 79.41 | V14: Credit Card | W14: 4 | X14: TRUE | Y14: Returned | Z14: Returned | AA14: 5 | AB14: 5 | AC14: 2024 | AD14: 45627 | AE14: 26-35 | AF14: 11-20% | AG14: =IF(N14=999,"Exclude","Include") -> Include | AH14: =IF(Z14="Returned",1,0) -> 1 | AI14: =IF(OR(Z14="Delivered",Z14="Returned"),1,0) -> 1 | AJ14: =IF(Z14="Cancelled",1,0) -> 0 | AK14: =1 -> 1
A15: ORD-04187 | B15: 45651 | C15: 45651 | D15: CUST58320 | E15: Pooja Sharma | H15: Other | I15: Other | J15: West | K15: Ahmedabad | L15: Furniture | M15: Sofa | N15: 8 | O15: 8 | P15: 14656.38 | Q15: 0.05 | R15: 100424.49 | S15: 22861.06 | T15: 0.228 | U15: 54.81 | V15: Debit Card | W15: 1 | X15: FALSE | Y15: Delivered | Z15: Delivered | AA15: 6 | AB15: 6 | AC15: 2024 | AD15: 45627 | AE15: Unknown | AF15: 1-10% | AG15: =IF(N15=999,"Exclude","Include") -> Include | AH15: =IF(Z15="Returned",1,0) -> 0 | AI15: =IF(OR(Z15="Delivered",Z15="Returned"),1,0) -> 1 | AJ15: =IF(Z15="Cancelled",1,0) -> 0 | AK15: =1 -> 1
A16: ORD-04186 | B16: 45651 | C16: 45651 | D16: CUST56795 | E16: Meera Das | F16: 26 | G16: 26 | H16: Other | I16: Other | J16: North | K16: Amritsar | L16: Sports | M16: Tennis Racket | N16: 1 | O16: 1 | P16: 5533.14 | Q16: 0.17 | R16: 4162.69 | S16: 628.33 | T16: 0.151 | U16: 62.44 | V16: EMI | W16: 4 | X16: FALSE | Y16: Cancelled | Z16: Cancelled | AA16: 6 | AB16: 6 | AC16: 2024 | AD16: 45627 | AE16: 26-35 | AF16: 11-20% | AG16: =IF(N16=999,"Exclude","Include") -> Include | AH16: =IF(Z16="Returned",1,0) -> 0 | AI16: =IF(OR(Z16="Delivered",Z16="Returned"),1,0) -> 0 | AJ16: =IF(Z16="Cancelled",1,0) -> 1 | AK16: =1 -> 1
A17: ORD-04185 | B17: 45651 | C17: 45651 | D17: CUST09877 | E17: Nisha Mehta | F17: 11 | G17: 11 | H17: Male | I17: Male | J17: South | K17: Bangalore | L17: Clothing | M17: Kurta | N17: 6 | O17: 6 | P17: 914.9 | Q17: 0.29 | R17: 3583.35 | S17: 1511.38 | T17: 0.422 | U17: 91.61 | V17: Credit Card | W17: 5 | X17: FALSE | Y17: Shipped | Z17: Shipped | AA17: 6 | AB17: 6 | AC17: 2024 | AD17: 45627 | AE17: <18 | AF17: 21-30% | AG17: =IF(N17=999,"Exclude","Include") -> Include | AH17: =IF(Z17="Returned",1,0) -> 0 | AI17: =IF(OR(Z17="Delivered",Z17="Returned"),1,0) -> 0 | AJ17: =IF(Z17="Cancelled",1,0) -> 0 | AK17: =1 -> 1
A18: ORD-04182 | B18: 45650 | C18: 45650 | D18: CUST64358 | E18: Deepa Chatterjee | F18: 38 | G18: 38 | H18: Other | I18: Other | J18: North | K18: Ludhiana | L18: Groceries | M18: Flour | N18: 9 | O18: 9 | P18: 65.35 | Q18: 0 | R18: 550.67 | S18: 52.12 | T18: 0.095 | U18: 35.68 | V18: Net Banking | W18: 5 | X18: FALSE | Y18: Delivered | Z18: Delivered | AC18: 2024 | AD18: 45627 | AE18: 36-45 | AF18: 0 | AG18: =IF(N18=999,"Exclude","Include") -> Include | AH18: =IF(Z18="Returned",1,0) -> 0 | AI18: =IF(OR(Z18="Delivered",Z18="Returned"),1,0) -> 1 | AJ18: =IF(Z18="Cancelled",1,0) -> 0 | AK18: =1 -> 1
A19: ORD-04183 | B19: 45650 | C19: 45650 | D19: CUST82683 | E19: Kavya Patel | F19: 60 | G19: 60 | H19: Female | I19: Female | J19: Central | K19: Indore | L19: Books | M19: Biography | N19: 1 | O19: 1 | P19: 1309.19 | Q19: 0.23 | R19: 976.81 | S19: 529.27 | T19: 0.542 | U19: 64.44 | V19: Debit Card | W19: 2 | X19: FALSE | Y19: Delivered | Z19: Delivered | AA19: 7 | AB19: 7 | AC19: 2024 | AD19: 45627 | AE19: 46-60 | AF19: 21-30% | AG19: =IF(N19=999,"Exclude","Include") -> Include | AH19: =IF(Z19="Returned",1,0) -> 0 | AI19: =IF(OR(Z19="Delivered",Z19="Returned"),1,0) -> 1 | AJ19: =IF(Z19="Cancelled",1,0) -> 0 | AK19: =1 -> 1
A20: ORD-04184 | B20: December 24, 2024 | C20: 45650 | D20: CUST57246 | E20: Shreya Patel | F20: 34 | G20: 34 | H20: m | I20: Male | J20: East | K20: Guwahati | L20: Furniture | M20: Chair | N20: 9 | O20: 9 | P20: 17949.6 | Q20: 0.08 | R20: 129636.87 | S20: 41301.73 | T20: 0.319 | U20: 79.91 | V20: UPI | W20: 5 | X20: FALSE | Y20: Delivered | Z20: Delivered | AA20: 3 | AB20: 3 | AC20: 2024 | AD20: 45627 | AE20: 26-35 | AF20: 1-10% | AG20: =IF(N20=999,"Exclude","Include") -> Include | AH20: =IF(Z20="Returned",1,0) -> 0 | AI20: =IF(OR(Z20="Delivered",Z20="Returned"),1,0) -> 1 | AJ20: =IF(Z20="Cancelled",1,0) -> 0 | AK20: =1 -> 1
A21: ORD-04181 | B21: 45649 | C21: 45649 | D21: CUST34843 | E21: Rohan Chatterjee | F21: 5 | G21: 5 | H21: Male | I21: Male | J21: South | K21: Bangalore | L21: Beauty | M21: Sunscreen | N21: 4 | O21: 4 | P21: 270.17 | Q21: 0.27 | R21: 766.64 | S21: 297.01 | T21: 0.387 | U21: 54.45 | V21: UPI | W21: 2 | X21: FALSE | Y21: Pending | Z21: Pending | AA21: 3 | AB21: 3 | AC21: 2024 | AD21: 45627 | AE21: <18 | AF21: 21-30% | AG21: =IF(N21=999,"Exclude","Include") -> Include | AH21: =IF(Z21="Returned",1,0) -> 0 | AI21: =IF(OR(Z21="Delivered",Z21="Returned"),1,0) -> 0 | AJ21: =IF(Z21="Cancelled",1,0) -> 0 | AK21: =1 -> 1
A22: ORD-04178 | B22: 45648 | C22: 45648 | D22: CUST11016 | E22: Amit Verma | F22: 53 | G22: 53 | H22: Male | I22: Male | J22: West | K22: Mumbai | L22: Beauty | M22: Shampoo | N22: 3 | O22: 3 | P22: 855.83 | Q22: 0.14 | R22: 2047.13 | S22: 587.72 | T22: 0.287 | U22: 59.05 | V22: Net Banking | W22: 4 | X22: FALSE | Y22: Pending | Z22: Pending | AA22: 6 | AB22: 6 | AC22: 2024 | AD22: 45627 | AE22: 46-60 | AF22: 11-20% | AG22: =IF(N22=999,"Exclude","Include") -> Include | AH22: =IF(Z22="Returned",1,0) -> 0 | AI22: =IF(OR(Z22="Delivered",Z22="Returned"),1,0) -> 0 | AJ22: =IF(Z22="Cancelled",1,0) -> 0 | AK22: =1 -> 1
A23: ORD-04180 | B23: 45648 | C23: 45648 | D23: CUST01003 | E23: Priya Pillai | F23: 28 | G23: 28 | H23: Female | I23: Female | J23: Central | K23: Bhopal | L23: Groceries | M23: Sugar | N23: 10 | O23: 10 | P23: 194.61 | Q23: 0.27 | R23: 1329.87 | S23: 143.25 | T23: 0.108 | U23: 23.86 | V23: EMI | W23: 2 | X23: FALSE | Y23: Delivered | Z23: Delivered | AA23: 5 | AB23: 5 | AC23: 2024 | AD23: 45627 | AE23: 26-35 | AF23: 21-30% | AG23: =IF(N23=999,"Exclude","Include") -> Include | AH23: =IF(Z23="Returned",1,0) -> 0 | AI23: =IF(OR(Z23="Delivered",Z23="Returned"),1,0) -> 1 | AJ23: =IF(Z23="Cancelled",1,0) -> 0 | AK23: =1 -> 1
A24: ORD-04179 | B24: 45648 | C24: 45648 | D24: CUST52695 | E24: Meera Mehta | F24: 47 | G24: 47 | H24: Male | I24: Male | J24: North | K24: Chandigarh | L24: Electronics | M24: Laptop | N24: 10 | O24: 10 | P24: 56887.12 | Q24: 0.33 | R24: 320072.27 | S24: 41433.48 | T24: 0.129 | U24: 58.41 | V24: Net Banking | W24: 1 | X24: FALSE | Y24: Delivered | Z24: Delivered | AA24: 6 | AB24: 6 | AC24: 2024 | AD24: 45627 | AE24: 46-60 | AF24: 31-40% | AG24: =IF(N24=999,"Exclude","Include") -> Include | AH24: =IF(Z24="Returned",1,0) -> 0 | AI24: =IF(OR(Z24="Delivered",Z24="Returned"),1,0) -> 1 | AJ24: =IF(Z24="Cancelled",1,0) -> 0 | AK24: =1 -> 1
A25: ORD-04177 | B25: 45647 | C25: 45647 | D25: CUST44560 | E25: Amit Verma | F25: 49 | G25: 49 | H25: female | I25: Female | J25: South | K25: Bangalore | L25: Sports | M25: Dumbbells | N25: 2 | O25: 2 | P25: 13057.02 | Q25: 0.35 | R25: 14206.67 | S25: 3578.76 | T25: 0.252 | U25: 69.31 | V25: Credit Card | W25: 5 | X25: FALSE | Y25: Delivered | Z25: Delivered | AA25: 10 | AB25: 10 | AC25: 2024 | AD25: 45627 | AE25: 46-60 | AF25: 31-40% | AG25: =IF(N25=999,"Exclude","Include") -> Include | AH25: =IF(Z25="Returned",1,0) -> 0 | AI25: =IF(OR(Z25="Delivered",Z25="Returned"),1,0) -> 1 | AJ25: =IF(Z25="Cancelled",1,0) -> 0 | AK25: =1 -> 1
A26: ORD-04176 | B26: 45647 | C26: 45647 | D26: CUST37046 | E26: Rohan Bhat | F26: 30 | G26: 30 | H26: Other | I26: Other | J26: West | K26: Surat | L26: Electronics | M26: Headphones | N26: 6 | O26: 6 | P26: 61234.43 | Q26: 0.24 | R26: 268632.52 | S26: 31422.9 | T26: 0.117 | U26: 48.82 | V26: Credit Card | X26: FALSE | Y26: Delivered | Z26: Delivered | AA26: 4 | AB26: 4 | AC26: 2024 | AD26: 45627 | AE26: 26-35 | AF26: 21-30% | AG26: =IF(N26=999,"Exclude","Include") -> Include | AH26: =IF(Z26="Returned",1,0) -> 0 | AI26: =IF(OR(Z26="Delivered",Z26="Returned"),1,0) -> 1 | AJ26: =IF(Z26="Cancelled",1,0) -> 0 | AK26: =1 -> 1
A27: ORD-04175 | B27: 45646 | C27: 45646 | D27: CUST38221 | E27: Pooja Kapoor | F27: 48 | G27: 48 | H27: Other | I27: Other | J27: North | K27: Ludhiana | L27: Beauty | M27: Lipstick | N27: 5 | O27: 5 | P27: 1283.61 | Q27: 0.36 | R27: 3770.64 | S27: 2025.41 | T27: 0.537 | U27: 50.14 | V27: Credit Card | W27: 4 | X27: FALSE | Y27: Delivered | Z27: Delivered | AA27: 8 | AB27: 8 | AC27: 2024 | AD27: 45627 | AE27: 46-60 | AF27: 31-40% | AG27: =IF(N27=999,"Exclude","Include") -> Include | AH27: =IF(Z27="Returned",1,0) -> 0 | AI27: =IF(OR(Z27="Delivered",Z27="Returned"),1,0) -> 1 | AJ27: =IF(Z27="Cancelled",1,0) -> 0 | AK27: =1 -> 1
A28: ORD-04174 | B28: 45645 | C28: 45645 | D28: CUST60428 | E28: Deepa Pillai | F28: 17 | G28: 17 | H28: Other | I28: Other | J28: South | K28: Kochi | L28: Furniture | M28: Bed Frame | N28: 5 | O28: 5 | P28: 22094.81 | Q28: 0.05 | R28: 95653.07 | S28: 32975.78 | T28: 0.345 | U28: 89.18 | V28: Net Banking | W28: 3 | X28: FALSE | Y28: Delivered | Z28: Delivered | AA28: 3 | AB28: 3 | AC28: 2024 | AD28: 45627 | AE28: <18 | AF28: 1-10% | AG28: =IF(N28=999,"Exclude","Include") -> Include | AH28: =IF(Z28="Returned",1,0) -> 0 | AI28: =IF(OR(Z28="Delivered",Z28="Returned"),1,0) -> 1 | AJ28: =IF(Z28="Cancelled",1,0) -> 0 | AK28: =1 -> 1
A29: ORD-04171 | B29: 45643 | C29: 45643 | D29: CUST15084 | E29: Nikhil Mishra | F29: 43 | G29: 43 | H29: Male | I29: Male | J29: South | K29: Kochi | L29: Clothing | M29: Jacket | N29: 5 | O29: 5 | P29: 3006.52 | Q29: 0.12 | R29: 10622.32 | S29: 4837.79 | T29: 0.455 | U29: 75.97 | V29: Credit Card | W29: 1 | X29: FALSE | Y29: Delivered | Z29: Delivered | AA29: 5 | AB29: 5 | AC29: 2024 | AD29: 45627 | AE29: 36-45 | AF29: 11-20% | AG29: =IF(N29=999,"Exclude","Include") -> Include | AH29: =IF(Z29="Returned",1,0) -> 0 | AI29: =IF(OR(Z29="Delivered",Z29="Returned"),1,0) -> 1 | AJ29: =IF(Z29="Cancelled",1,0) -> 0 | AK29: =1 -> 1
A30: ORD-04172 | B30: 45643 | C30: 45643 | D30: CUST07872 | E30: Meera Rao | F30: 32 | G30: 32 | H30: m | I30: Male | J30: North | K30: Ludhiana | L30: Beauty | M30: Lipstick | N30: 5 | O30: 5 | P30: 2144.13 | Q30: 0.1 | R30: 9449.37 | S30: 4541.29 | T30: 0.481 | U30: 19.04 | V30: Debit Card | X30: FALSE | Y30: Delivered | Z30: Delivered | AA30: 5 | AB30: 5 | AC30: 2024 | AD30: 45627 | AE30: 26-35 | AF30: 1-10% | AG30: =IF(N30=999,"Exclude","Include") -> Include | AH30: =IF(Z30="Returned",1,0) -> 0 | AI30: =IF(OR(Z30="Delivered",Z30="Returned"),1,0) -> 1 | AJ30: =IF(Z30="Cancelled",1,0) -> 0 | AK30: =1 -> 1
A31: ORD-04173 | B31: 45643 | C31: 45643 | D31: CUST95025 | E31: Aditya Kapoor | F31: 18 | G31: 18 | H31: Female | I31: Female | J31: North | K31: Ludhiana | L31: Furniture | M31: Sofa | N31: 6 | O31: 6 | P31: 29938.75 | Q31: 0.17 | R31: 139138.9 | S31: 44922.96 | T31: 0.323 | U31: 34.46 | V31: Cash on Delivery | W31: 1 | X31: FALSE | Y31: Delivered | Z31: Delivered | AA31: 9 | AB31: 9 | AC31: 2024 | AD31: 45627 | AE31: 18-25 | AF31: 11-20% | AG31: =IF(N31=999,"Exclude","Include") -> Include | AH31: =IF(Z31="Returned",1,0) -> 0 | AI31: =IF(OR(Z31="Delivered",Z31="Returned"),1,0) -> 1 | AJ31: =IF(Z31="Cancelled",1,0) -> 0 | AK31: =1 -> 1
A32: ORD-04169 | B32: 45642 | C32: 45642 | D32: CUST68700 | E32: Aditya Mehta | F32: 33 | G32: 33 | H32: Female | I32: Female | J32: South | K32: Bangalore | L32: Sports | M32: Football | N32: 9 | O32: 9 | P32: 7976.73 | R32: 57905.39 | S32: 13844.42 | T32: 0.239 | U32: 69.85 | V32: EMI | W32: 1 | X32: FALSE | Y32: Delivered | Z32: Delivered | AA32: 8 | AB32: 8 | AC32: 2024 | AD32: 45627 | AE32: 26-35 | AF32: No data | AG32: =IF(N32=999,"Exclude","Include") -> Include | AH32: =IF(Z32="Returned",1,0) -> 0 | AI32: =IF(OR(Z32="Delivered",Z32="Returned"),1,0) -> 1 | AJ32: =IF(Z32="Cancelled",1,0) -> 0 | AK32: =1 -> 1
A33: ORD-04170 | B33: 45642 | C33: 45642 | D33: CUST70820 | E33: Nikhil Iyer | F33: 14 | G33: 14 | H33: Male | I33: Male | J33: East | K33: Kolkata | L33: Clothing | M33: Jeans | N33: 4 | O33: 4 | P33: 1999.6 | Q33: 0.4 | R33: 4690.45 | S33: 1146.6 | T33: 0.244 | U33: 66.84 | V33: Net Banking | X33: FALSE | Y33: Delivered | Z33: Delivered | AC33: 2024 | AD33: 45627 | AE33: <18 | AF33: 31-40% | AG33: =IF(N33=999,"Exclude","Include") -> Include | AH33: =IF(Z33="Returned",1,0) -> 0 | AI33: =IF(OR(Z33="Delivered",Z33="Returned"),1,0) -> 1 | AJ33: =IF(Z33="Cancelled",1,0) -> 0 | AK33: =1 -> 1
A34: ORD-04167 | B34: 45641 | C34: 45641 | D34: CUST06213 | E34: Kavya Patel | F34: 29 | G34: 29 | H34: Other | I34: Other | J34: East | K34: Bhubaneswar | L34: Furniture | M34: Bed Frame | N34: 9 | O34: 9 | P34: 26558.96 | Q34: 0.12 | R34: 191023.49 | S34: 41485.81 | T34: 0.217 | U34: 110.49 | V34: Net Banking | W34: 3 | X34: TRUE | Y34: Returned | Z34: Returned | AA34: 6 | AB34: 6 | AC34: 2024 | AD34: 45627 | AE34: 26-35 | AF34: 11-20% | AG34: =IF(N34=999,"Exclude","Include") -> Include | AH34: =IF(Z34="Returned",1,0) -> 1 | AI34: =IF(OR(Z34="Delivered",Z34="Returned"),1,0) -> 1 | AJ34: =IF(Z34="Cancelled",1,0) -> 0 | AK34: =1 -> 1
A35: ORD-04165 | B35: 45641 | C35: 45641 | D35: CUST82149 | E35: Nisha Verma | F35: 38 | G35: 38 | H35: MALE | I35: Male | J35: East | K35: Bhubaneswar | L35: Electronics | M35: Smartwatch | N35: 4 | O35: 4 | P35: 62134.64 | Q35: 0.31 | R35: 151708.44 | S35: 17375.7 | T35: 0.115 | U35: 66.2 | V35: Net Banking | X35: FALSE | Y35: Delivered | Z35: Delivered | AA35: 1 | AB35: 1 | AC35: 2024 | AD35: 45627 | AE35: 36-45 | AF35: 31-40% | AG35: =IF(N35=999,"Exclude","Include") -> Include | AH35: =IF(Z35="Returned",1,0) -> 0 | AI35: =IF(OR(Z35="Delivered",Z35="Returned"),1,0) -> 1 | AJ35: =IF(Z35="Cancelled",1,0) -> 0 | AK35: =1 -> 1
A36: ORD-04168 | B36: 45641 | C36: 45641 | D36: CUST39751 | E36: Meera Iyer | H36: Female | I36: Female | J36: West | K36: Ahmedabad | L36: Sports | M36: Tennis Racket | N36: 2 | O36: 2 | P36: 10972.39 | Q36: 0.3 | R36: 11894.53 | S36: 2981.58 | T36: 0.251 | U36: 43.93 | V36: EMI | W36: 2 | X36: FALSE | Y36: Delivered | Z36: Delivered | AA36: 10 | AB36: 10 | AC36: 2024 | AD36: 45627 | AE36: Unknown | AF36: 21-30% | AG36: =IF(N36=999,"Exclude","Include") -> Include | AH36: =IF(Z36="Returned",1,0) -> 0 | AI36: =IF(OR(Z36="Delivered",Z36="Returned"),1,0) -> 1 | AJ36: =IF(Z36="Cancelled",1,0) -> 0 | AK36: =1 -> 1
A37: ORD-04166 | B37: 45641 | C37: 45641 | D37: CUST73620 | E37: Rohan Reddy | F37: 18 | G37: 18 | H37: Female | I37: Female | J37: South | K37: Bangalore | L37: Clothing | M37: T-Shirt | N37: 6 | O37: 6 | P37: 841.47 | Q37: 0.12 | R37: 4321.42 | S37: 1728.55 | T37: 0.4 | U37: 70.62 | V37: UPI | W37: 1 | X37: FALSE | Y37: Delivered | Z37: Delivered | AA37: 2 | AB37: 2 | AC37: 2024 | AD37: 45627 | AE37: 18-25 | AF37: 11-20% | AG37: =IF(N37=999,"Exclude","Include") -> Include | AH37: =IF(Z37="Returned",1,0) -> 0 | AI37: =IF(OR(Z37="Delivered",Z37="Returned"),1,0) -> 1 | AJ37: =IF(Z37="Cancelled",1,0) -> 0 | AK37: =1 -> 1
A38: ORD-04164 | B38: 45640 | C38: 45640 | D38: CUST96903 | E38: Deepa Kapoor | F38: 46 | G38: 46 | H38: Other | I38: Other | J38: North | K38: Amritsar | L38: Furniture | M38: Chair | N38: 1 | O38: 1 | P38: 9449.94 | Q38: 0.15 | R38: 7223.61 | S38: 2224.51 | T38: 0.308 | U38: 32.57 | V38: UPI | W38: 1 | X38: TRUE | Y38: Returned | Z38: Returned | AA38: 2 | AB38: 2 | AC38: 2024 | AD38: 45627 | AE38: 46-60 | AF38: 11-20% | AG38: =IF(N38=999,"Exclude","Include") -> Include | AH38: =IF(Z38="Returned",1,0) -> 1 | AI38: =IF(OR(Z38="Delivered",Z38="Returned"),1,0) -> 1 | AJ38: =IF(Z38="Cancelled",1,0) -> 0 | AK38: =1 -> 1
A39: ORD-04160 | B39: 45637 | C39: 45637 | D39: CUST91116 | E39: Rohan Patel | F39: 36 | G39: 36 | H39: Male | I39: Male | J39: South | K39: Hyderabad | L39: Books | M39: Biography | N39: 7 | O39: 7 | P39: 609.79 | Q39: 0.25 | R39: 2905.61 | S39: 1079.08 | T39: 0.371 | U39: 68.86 | V39: UPI | W39: 3 | X39: FALSE | Y39: Delivered | Z39: Delivered | AA39: 7 | AB39: 7 | AC39: 2024 | AD39: 45627 | AE39: 36-45 | AF39: 21-30% | AG39: =IF(N39=999,"Exclude","Include") -> Include | AH39: =IF(Z39="Returned",1,0) -> 0 | AI39: =IF(OR(Z39="Delivered",Z39="Returned"),1,0) -> 1 | AJ39: =IF(Z39="Cancelled",1,0) -> 0 | AK39: =1 -> 1
A40: ORD-04161 | B40: 45637 | C40: 45637 | D40: CUST28262 | E40: Aarav Patel | F40: 22 | G40: 22 | H40: Male | I40: Male | J40: South | K40: Chennai | L40: Groceries | M40: Rice (5kg) | N40: 3 | O40: 3 | P40: 55.73 | Q40: 0.25 | R40: 132.26 | S40: 9.16 | T40: 0.069 | U40: 67.07 | V40: Credit Card | W40: 4 | X40: TRUE | Y40: Returned | Z40: Returned | AA40: 9 | AB40: 9 | AC40: 2024 | AD40: 45627 | AE40: 18-25 | AF40: 21-30% | AG40: =IF(N40=999,"Exclude","Include") -> Include | AH40: =IF(Z40="Returned",1,0) -> 1 | AI40: =IF(OR(Z40="Delivered",Z40="Returned"),1,0) -> 1 | AJ40: =IF(Z40="Cancelled",1,0) -> 0 | AK40: =1 -> 1
A41: ORD-04159 | B41: 45637 | C41: 45637 | D41: CUST56892 | E41: Karan Gupta | F41: 19 | G41: 19 | H41: Male | I41: Male | J41: South | K41: Bangalore | L41: Electronics | M41: Camera | N41: 10 | O41: 10 | P41: 19562.84 | Q41: 0.24 | R41: 159763.82 | S41: 22214.02 | T41: 0.139 | U41: 80.65 | V41: EMI | W41: 5 | X41: FALSE | Y41: Shipped | Z41: Shipped | AA41: 10 | AB41: 10 | AC41: 2024 | AD41: 45627 | AE41: 18-25 | AF41: 21-30% | AG41: =IF(N41=999,"Exclude","Include") -> Include | AH41: =IF(Z41="Returned",1,0) -> 0 | AI41: =IF(OR(Z41="Delivered",Z41="Returned"),1,0) -> 0 | AJ41: =IF(Z41="Cancelled",1,0) -> 0 | AK41: =1 -> 1
A42: ORD-04162 | B42: 45637 | C42: 45637 | D42: CUST14967 | E42: Kavya Kumar | F42: 15 | G42: 15 | H42: Other | I42: Other | J42: North | K42: Delhi | L42: Groceries | M42: Sugar | N42: 10 | O42: 10 | P42: 273.14 | Q42: 0.28 | R42: 1532.4 | S42: 100.08 | T42: 0.065 | U42: 54.94 | V42: EMI | W42: 4 | X42: FALSE | Y42: Delivered | Z42: Delivered | AA42: 5 | AB42: 5 | AC42: 2024 | AD42: 45627 | AE42: <18 | AF42: 21-30% | AG42: =IF(N42=999,"Exclude","Include") -> Include | AH42: =IF(Z42="Returned",1,0) -> 0 | AI42: =IF(OR(Z42="Delivered",Z42="Returned"),1,0) -> 1 | AJ42: =IF(Z42="Cancelled",1,0) -> 0 | AK42: =1 -> 1
A43: ORD-04163 | B43: 45637 | C43: 45637 | D43: CUST00013 | E43: Rahul Nair | F43: 29 | G43: 29 | H43: Female | I43: Female | J43: South | K43: Hyderabad | L43: Books | M43: Self-Help Book | P43: 294.33 | Q43: 0.19 | R43: 222.9 | S43: 77.47 | T43: 0.348 | U43: 95.45 | V43: Net Banking | W43: 2 | X43: FALSE | Y43: Delivered | Z43: Delivered | AA43: 2 | AB43: 2 | AC43: 2024 | AD43: 45627 | AE43: 26-35 | AF43: 11-20% | AG43: =IF(N43=999,"Exclude","Include") -> Include | AH43: =IF(Z43="Returned",1,0) -> 0 | AI43: =IF(OR(Z43="Delivered",Z43="Returned"),1,0) -> 1 | AJ43: =IF(Z43="Cancelled",1,0) -> 0 | AK43: =1 -> 1
A44: ORD-04158 | B44: 45636 | C44: 45636 | D44: CUST75042 | E44: Pooja Verma | F44: 44 | G44: 44 | H44: Female | I44: Female | J44: Central | K44: Nagpur | L44: Books | M44: Self-Help Book | N44: 7 | O44: 7 | P44: 612.7 | Q44: 0.22 | R44: 3224.82 | S44: 991.03 | T44: 0.307 | U44: 55.8 | V44: Credit Card | W44: 5 | X44: FALSE | Y44: Delivered | Z44: Delivered | AA44: 4 | AB44: 4 | AC44: 2024 | AD44: 45627 | AE44: 36-45 | AF44: 21-30% | AG44: =IF(N44=999,"Exclude","Include") -> Include | AH44: =IF(Z44="Returned",1,0) -> 0 | AI44: =IF(OR(Z44="Delivered",Z44="Returned"),1,0) -> 1 | AJ44: =IF(Z44="Cancelled",1,0) -> 0 | AK44: =1 -> 1
A45: ORD-04157 | B45: 45636 | C45: 45636 | D45: CUST48612 | E45: Nisha Bose | F45: 56 | G45: 56 | H45: Male | I45: Male | J45: South | K45: Hyderabad | L45: Furniture | M45: Bookshelf | N45: 6 | O45: 6 | P45: 10501.71 | Q45: 0.38 | R45: 35801.2 | S45: 13056.43 | T45: 0.365 | U45: 75.18 | V45: Credit Card | W45: 1 | X45: FALSE | Y45: Cancelled | Z45: Cancelled | AA45: 6 | AB45: 6 | AC45: 2024 | AD45: 45627 | AE45: 46-60 | AF45: 31-40% | AG45: =IF(N45=999,"Exclude","Include") -> Include | AH45: =IF(Z45="Returned",1,0) -> 0 | AI45: =IF(OR(Z45="Delivered",Z45="Returned"),1,0) -> 0 | AJ45: =IF(Z45="Cancelled",1,0) -> 1 | AK45: =1 -> 1
A46: ORD-04154 | B46: 45635 | C46: 45635 | D46: CUST34894 | E46: Nikhil Bose | F46: 18 | G46: 18 | H46: Other | I46: Other | J46: East | K46: Bhubaneswar | L46: Books | M46: Cook Book | N46: 2 | O46: 2 | P46: 1034.18 | Q46: 0.33 | R46: 1184.8 | S46: 369.59 | T46: 0.312 | U46: 65.48 | V46: Credit Card | W46: 5 | X46: FALSE | Y46: Delivered | Z46: Delivered | AA46: 3 | AB46: 3 | AC46: 2024 | AD46: 45627 | AE46: 18-25 | AF46: 31-40% | AG46: =IF(N46=999,"Exclude","Include") -> Include | AH46: =IF(Z46="Returned",1,0) -> 0 | AI46: =IF(OR(Z46="Delivered",Z46="Returned"),1,0) -> 1 | AJ46: =IF(Z46="Cancelled",1,0) -> 0 | AK46: =1 -> 1
A47: ORD-04155 | B47: 45635 | C47: 45635 | D47: CUST98534 | E47: Rohan Bhat | F47: 49 | G47: 49 | H47: Other | I47: Other | J47: Central | K47: Indore | L47: Beauty | M47: Lipstick | N47: 7 | O47: 7 | P47: 2138.83 | Q47: 0.26 | R47: 10637.74 | S47: 4567.68 | T47: 0.429 | U47: 39.39 | V47: Debit Card | W47: 2 | X47: FALSE | Y47: Cancelled | Z47: Cancelled | AA47: 7 | AB47: 7 | AC47: 2024 | AD47: 45627 | AE47: 46-60 | AF47: 21-30% | AG47: =IF(N47=999,"Exclude","Include") -> Include | AH47: =IF(Z47="Returned",1,0) -> 0 | AI47: =IF(OR(Z47="Delivered",Z47="Returned"),1,0) -> 0 | AJ47: =IF(Z47="Cancelled",1,0) -> 1 | AK47: =1 -> 1
A48: ORD-04156 | B48: 45635 | C48: 45635 | D48: CUST37501 | E48: Rohan Bose | F48: 40 | G48: 40 | H48: Other | I48: Other | J48: Central | K48: Raipur | L48: Electronics | M48: Tablet | N48: 4 | O48: 4 | P48: 23593.16 | Q48: 0.39 | R48: 50867.37 | S48: 6623.39 | T48: 0.13 | U48: 41.37 | V48: Net Banking | W48: 4 | X48: FALSE | Y48: Delivered | Z48: Delivered | AA48: 9 | AB48: 9 | AC48: 2024 | AD48: 45627 | AE48: 36-45 | AF48: 31-40% | AG48: =IF(N48=999,"Exclude","Include") -> Include | AH48: =IF(Z48="Returned",1,0) -> 0 | AI48: =IF(OR(Z48="Delivered",Z48="Returned"),1,0) -> 1 | AJ48: =IF(Z48="Cancelled",1,0) -> 0 | AK48: =1 -> 1
A49: ORD-04153 | B49: 45634 | C49: 45634 | D49: CUST73466 | E49: Aditya Pillai | F49: 24 | G49: 24 | H49: M | I49: Male | J49: West | K49: Pune | L49: Groceries | M49: Dal (1kg) | N49: 10 | O49: 10 | P49: 390.96 | Q49: 0.37 | R49: 2025.46 | S49: 195.36 | T49: 0.096 | U49: 83.81 | V49: Credit Card | W49: 2 | X49: FALSE | Y49: Delivered | Z49: Delivered | AA49: 1 | AB49: 1 | AC49: 2024 | AD49: 45627 | AE49: 18-25 | AF49: 31-40% | AG49: =IF(N49=999,"Exclude","Include") -> Include | AH49: =IF(Z49="Returned",1,0) -> 0 | AI49: =IF(OR(Z49="Delivered",Z49="Returned"),1,0) -> 1 | AJ49: =IF(Z49="Cancelled",1,0) -> 0 | AK49: =1 -> 1
A50: ORD-04151 | B50: 45633 | C50: 45633 | D50: CUST43686 | E50: Nikhil Singh | F50: 23 | G50: 23 | H50: Other | I50: Other | J50: North | K50: Delhi | L50: Groceries | M50: Rice (5kg) | N50: 4 | O50: 4 | P50: 471.4 | Q50: 0.3 | R50: 1216.57 | S50: 70.68 | T50: 0.058 | U50: 52.55 | V50: EMI | W50: 4 | X50: FALSE | Y50: Delivered | Z50: Delivered | AA50: 9 | AB50: 9 | AC50: 2024 | AD50: 45627 | AE50: 18-25 | AF50: 21-30% | AG50: =IF(N50=999,"Exclude","Include") -> Include | AH50: =IF(Z50="Returned",1,0) -> 0 | AI50: =IF(OR(Z50="Delivered",Z50="Returned"),1,0) -> 1 | AJ50: =IF(Z50="Cancelled",1,0) -> 0 | AK50: =1 -> 1
A51: ORD-04149 | B51: 45633 | C51: 45633 | D51: CUST54782 | E51: Karan Verma | F51: 37 | G51: 37 | H51: FEMALE | I51: Female | J51: Central | K51: Indore | L51: Books | M51: Textbook | N51: 8 | O51: 8 | P51: 519.05 | Q51: 0.33 | R51: 2627.87 | S51: 1117.94 | T51: 0.425 | U51: 51.28 | V51: Debit Card | W51: 2 | X51: FALSE | Y51: Delivered | Z51: Delivered | AA51: 10 | AB51: 10 | AC51: 2024 | AD51: 45627 | AE51: 36-45 | AF51: 31-40% | AG51: =IF(N51=999,"Exclude","Include") -> Include | AH51: =IF(Z51="Returned",1,0) -> 0 | AI51: =IF(OR(Z51="Delivered",Z51="Returned"),1,0) -> 1 | AJ51: =IF(Z51="Cancelled",1,0) -> 0 | AK51: =1 -> 1
A52: ORD-04152 | B52: 45633 | C52: 45633 | D52: CUST27678 | E52: Kavya Kapoor | F52: 39 | G52: 39 | H52: Other | I52: Other | J52: South | K52: Hyderabad | L52: Groceries | M52: Tea | N52: 6 | O52: 6 | P52: 199.94 | Q52: 0.07 | R52: 1058.44 | S52: 90.06 | T52: 0.085 | U52: 70.92 | V52: Credit Card | W52: 3 | X52: FALSE | Y52: Shipped | Z52: Shipped | AA52: 10 | AB52: 10 | AC52: 2024 | AD52: 45627 | AE52: 36-45 | AF52: 1-10% | AG52: =IF(N52=999,"Exclude","Include") -> Include | AH52: =IF(Z52="Returned",1,0) -> 0 | AI52: =IF(OR(Z52="Delivered",Z52="Returned"),1,0) -> 0 | AJ52: =IF(Z52="Cancelled",1,0) -> 0 | AK52: =1 -> 1
A53: ORD-04150 | B53: 45633 | C53: 45633 | D53: CUST41606 | E53: Arjun Verma | F53: 26 | G53: 26 | H53: Female | I53: Female | J53: North | K53: Ludhiana | L53: Electronics | M53: Headphones | N53: 2 | O53: 2 | P53: 51176.53 | Q53: 0.12 | R53: 72400.09 | S53: 8619.13 | T53: 0.119 | U53: 59.77 | V53: Cash on Delivery | W53: 2 | X53: FALSE | Y53: Delivered | Z53: Delivered | AA53: 3 | AB53: 3 | AC53: 2024 | AD53: 45627 | AE53: 26-35 | AF53: 11-20% | AG53: =IF(N53=999,"Exclude","Include") -> Include | AH53: =IF(Z53="Returned",1,0) -> 0 | AI53: =IF(OR(Z53="Delivered",Z53="Returned"),1,0) -> 1 | AJ53: =IF(Z53="Cancelled",1,0) -> 0 | AK53: =1 -> 1
A54: ORD-04148 | B54: 45633 | C54: 45633 | D54: CUST97586 | E54: Ananya Mishra | F54: 33 | G54: 33 | H54: Female | I54: Female | J54: North | K54: Ludhiana | L54: Clothing | M54: T-Shirt | N54: 5 | O54: 5 | P54: 614.15 | Q54: 0.17 | R54: 2315.9 | S54: 981.99 | T54: 0.424 | U54: 65.63 | V54: UPI | W54: 1 | X54: TRUE | Y54: Returned | Z54: Returned | AA54: 8 | AB54: 8 | AC54: 2024 | AD54: 45627 | AE54: 26-35 | AF54: 11-20% | AG54: =IF(N54=999,"Exclude","Include") -> Include | AH54: =IF(Z54="Returned",1,0) -> 1 | AI54: =IF(OR(Z54="Delivered",Z54="Returned"),1,0) -> 1 | AJ54: =IF(Z54="Cancelled",1,0) -> 0 | AK54: =1 -> 1
A55: ORD-04147 | B55: 45632 | C55: 45632 | D55: CUST95344 | E55: Ananya Reddy | F55: 32 | G55: 32 | H55: Other | I55: Other | J55: West | K55: Surat | L55: Beauty | M55: Lipstick | N55: 8 | O55: 8 | P55: 1064.92 | Q55: 0.37 | R55: 5754.84 | S55: 2941.97 | T55: 0.511 | U55: 55.05 | V55: Cash on Delivery | W55: 5 | X55: FALSE | Y55: Delivered | Z55: Delivered | AA55: 5 | AB55: 5 | AC55: 2024 | AD55: 45627 | AE55: 26-35 | AF55: 31-40% | AG55: =IF(N55=999,"Exclude","Include") -> Include | AH55: =IF(Z55="Returned",1,0) -> 0 | AI55: =IF(OR(Z55="Delivered",Z55="Returned"),1,0) -> 1 | AJ55: =IF(Z55="Cancelled",1,0) -> 0 | AK55: =1 -> 1
A56: ORD-04146 | B56: 45632 | C56: 45632 | D56: CUST52053 | E56: Nikhil Joshi | F56: 18 | G56: 18 | H56: Male | I56: Male | J56: South | K56: Hyderabad | L56: Beauty | M56: Face Cream | N56: 2 | O56: 2 | P56: 1657.33 | Q56: 0.02 | R56: 3020.21 | S56: 1521.99 | T56: 0.504 | U56: 48.9 | V56: UPI | W56: 5 | X56: FALSE | Y56: Shipped | Z56: Shipped | AA56: 4 | AB56: 4 | AC56: 2024 | AD56: 45627 | AE56: 18-25 | AF56: 1-10% | AG56: =IF(N56=999,"Exclude","Include") -> Include | AH56: =IF(Z56="Returned",1,0) -> 0 | AI56: =IF(OR(Z56="Delivered",Z56="Returned"),1,0) -> 0 | AJ56: =IF(Z56="Cancelled",1,0) -> 0 | AK56: =1 -> 1
A57: ORD-04145 | B57: December 05, 2024 | C57: 45631 | D57: CUST52922 | E57: Vikram Shah | F57: 999 | H57: Male | I57: Male | J57: East | K57: Kolkata | L57: Sports | M57: Tennis Racket | N57: 7 | O57: 7 | P57: 13857.65 | Q57: 0.09 | R57: 81878.9 | S57: 20918.31 | T57: 0.255 | U57: 72.38 | V57: Debit Card | W57: 5 | X57: FALSE | Y57: Pending | Z57: Pending | AA57: 8 | AB57: 8 | AC57: 2024 | AD57: 45627 | AE57: Unknown | AF57: 1-10% | AG57: =IF(N57=999,"Exclude","Include") -> Include | AH57: =IF(Z57="Returned",1,0) -> 0 | AI57: =IF(OR(Z57="Delivered",Z57="Returned"),1,0) -> 0 | AJ57: =IF(Z57="Cancelled",1,0) -> 0 | AK57: =1 -> 1
A58: ORD-04144 | B58: 45631 | C58: 45631 | D58: CUST34339 | E58: Rahul Shah | F58: 46 | G58: 46 | H58: Other | I58: Other | J58: West | K58: Pune | L58: Groceries | M58: Dal (1kg) | N58: 3 | O58: 3 | P58: 461.92 | Q58: 0.09 | R58: 1136.17 | S58: 111.05 | T58: 0.098 | U58: 92.19 | V58: Net Banking | X58: FALSE | Y58: Cancelled | Z58: Cancelled | AA58: 1 | AB58: 1 | AC58: 2024 | AD58: 45627 | AE58: 46-60 | AF58: 1-10% | AG58: =IF(N58=999,"Exclude","Include") -> Include | AH58: =IF(Z58="Returned",1,0) -> 0 | AI58: =IF(OR(Z58="Delivered",Z58="Returned"),1,0) -> 0 | AJ58: =IF(Z58="Cancelled",1,0) -> 1 | AK58: =1 -> 1
A59: ORD-04137 | B59: 45630 | C59: 45630 | D59: CUST62051 | E59: Ananya Pillai | F59: 5 | G59: 5 | H59: Other | I59: Other | J59: Central | K59: Bhopal | L59: Electronics | M59: Tablet | N59: 4 | O59: 4 | P59: 51581.35 | Q59: 0.38 | R59: 131067.26 | S59: 15238.43 | T59: 0.116 | U59: 72.66 | V59: Net Banking | W59: 4 | X59: TRUE | Y59: Returned | Z59: Returned | AA59: 8 | AB59: 8 | AC59: 2024 | AD59: 45627 | AE59: <18 | AF59: 31-40% | AG59: =IF(N59=999,"Exclude","Include") -> Include | AH59: =IF(Z59="Returned",1,0) -> 1 | AI59: =IF(OR(Z59="Delivered",Z59="Returned"),1,0) -> 1 | AJ59: =IF(Z59="Cancelled",1,0) -> 0 | AK59: =1 -> 1
A60: ORD-04141 | B60: 45630 | C60: 45630 | D60: CUST72168 | E60: Shreya Bhat | H60: m | I60: Male | J60: Central | K60: Nagpur | L60: Groceries | M60: Sugar | N60: 4 | O60: 4 | P60: 242.65 | R60: 854.73 | S60: 91.72 | T60: 0.107 | U60: 48.21 | V60: Net Banking | W60: 1 | X60: TRUE | Y60: Returned | Z60: Returned | AA60: 1 | AB60: 1 | AC60: 2024 | AD60: 45627 | AE60: Unknown | AF60: No data | AG60: =IF(N60=999,"Exclude","Include") -> Include | AH60: =IF(Z60="Returned",1,0) -> 1 | AI60: =IF(OR(Z60="Delivered",Z60="Returned"),1,0) -> 1 | AJ60: =IF(Z60="Cancelled",1,0) -> 0 | AK60: =1 -> 1
A61: ORD-04139 | B61: 45630 | C61: 45630 | D61: CUST95283 | E61: Ananya Chatterjee | F61: 31 | G61: 31 | H61: Male | I61: Male | J61: Central | K61: Bhopal | L61: Sports | M61: Football | P61: 3886.22 | Q61: 0.24 | R61: 2473 | S61: 489.55 | T61: 0.198 | U61: 40.87 | V61: Debit Card | W61: 4 | X61: TRUE | Y61: Returned | Z61: Returned | AA61: 4 | AB61: 4 | AC61: 2024 | AD61: 45627 | AE61: 26-35 | AF61: 21-30% | AG61: =IF(N61=999,"Exclude","Include") -> Include | AH61: =IF(Z61="Returned",1,0) -> 1 | AI61: =IF(OR(Z61="Delivered",Z61="Returned"),1,0) -> 1 | AJ61: =IF(Z61="Cancelled",1,0) -> 0 | AK61: =1 -> 1
A62: ORD-04140 | B62: 45630 | C62: 45630 | D62: CUST10076 | E62: Sanjay Iyer | F62: 47 | G62: 47 | H62: Male | I62: Male | J62: Central | K62: Raipur | L62: Beauty | M62: Shampoo | N62: 9 | O62: 9 | P62: 173.38 | Q62: 0.35 | R62: 967.63 | S62: 355.07 | T62: 0.367 | U62: 33.17 | V62: Cash on Delivery | W62: 5 | X62: FALSE | Y62: Cancelled | Z62: Cancelled | AA62: 10 | AB62: 10 | AC62: 2024 | AD62: 45627 | AE62: 46-60 | AF62: 31-40% | AG62: =IF(N62=999,"Exclude","Include") -> Include | AH62: =IF(Z62="Returned",1,0) -> 0 | AI62: =IF(OR(Z62="Delivered",Z62="Returned"),1,0) -> 0 | AJ62: =IF(Z62="Cancelled",1,0) -> 1 | AK62: =1 -> 1
A63: ORD-04142 | B63: 45630 | C63: 45630 | D63: CUST18673 | E63: Sanjay Joshi | F63: 19 | G63: 19 | H63: Other | I63: Other | J63: North | K63: Ludhiana | L63: Beauty | M63: Face Cream | N63: 9 | O63: 9 | P63: 1593.35 | Q63: 0.06 | R63: 10203.46 | S63: 4094.58 | T63: 0.401 | U63: 42.17 | V63: Credit Card | W63: 3 | X63: FALSE | Y63: Delivered | Z63: Delivered | AA63: 2 | AB63: 2 | AC63: 2024 | AD63: 45627 | AE63: 18-25 | AF63: 1-10% | AG63: =IF(N63=999,"Exclude","Include") -> Include | AH63: =IF(Z63="Returned",1,0) -> 0 | AI63: =IF(OR(Z63="Delivered",Z63="Returned"),1,0) -> 1 | AJ63: =IF(Z63="Cancelled",1,0) -> 0 | AK63: =1 -> 1
A64: ORD-04143 | B64: 45630 | C64: 45630 | D64: CUST39988 | E64: Amit Chatterjee | F64: 20 | G64: 20 | H64: Male | I64: Male | J64: East | K64: Guwahati | L64: Furniture | M64: Bed Frame | N64: 9 | O64: 9 | P64: 31889.55 | Q64: 0.03 | R64: 231659.35 | S64: 73647.32 | T64: 0.318 | U64: 82.21 | V64: Credit Card | W64: 4 | X64: FALSE | Y64: Delivered | Z64: Delivered | AA64: 3 | AB64: 3 | AC64: 2024 | AD64: 45627 | AE64: 18-25 | AF64: 1-10% | AG64: =IF(N64=999,"Exclude","Include") -> Include | AH64: =IF(Z64="Returned",1,0) -> 0 | AI64: =IF(OR(Z64="Delivered",Z64="Returned"),1,0) -> 1 | AJ64: =IF(Z64="Cancelled",1,0) -> 0 | AK64: =1 -> 1
A65: ORD-04138 | B65: 45630 | C65: 45630 | D65: CUST97139 | E65: Rohan Bhat | F65: 25 | G65: 25 | H65: Male | I65: Male | J65: Central | K65: Nagpur | L65: Books | M65: Cook Book | N65: 1 | O65: 1 | P65: 395.88 | Q65: 0.05 | R65: 323.03 | S65: 152.9 | T65: 0.473 | U65: 52.45 | V65: Cash on Delivery | W65: 3 | X65: FALSE | Y65: Delivered | Z65: Delivered | AA65: 5 | AB65: 5 | AC65: 2024 | AD65: 45627 | AE65: 18-25 | AF65: 1-10% | AG65: =IF(N65=999,"Exclude","Include") -> Include | AH65: =IF(Z65="Returned",1,0) -> 0 | AI65: =IF(OR(Z65="Delivered",Z65="Returned"),1,0) -> 1 | AJ65: =IF(Z65="Cancelled",1,0) -> 0 | AK65: =1 -> 1
A66: ORD-04136 | B66: 45629 | C66: 45629 | D66: CUST52875 | E66: Shreya Mishra | F66: 24 | G66: 24 | H66: Female | I66: Female | J66: Central | K66: Bhopal | L66: Books | M66: Self-Help Book | N66: 2 | O66: 2 | P66: 585.2 | Q66: 0.28 | R66: 801.85 | S66: 375.39 | T66: 0.468 | U66: 29.42 | V66: Debit Card | W66: 1 | X66: FALSE | Y66: Cancelled | Z66: Cancelled | AA66: 2 | AB66: 2 | AC66: 2024 | AD66: 45627 | AE66: 18-25 | AF66: 21-30% | AG66: =IF(N66=999,"Exclude","Include") -> Include | AH66: =IF(Z66="Returned",1,0) -> 0 | AI66: =IF(OR(Z66="Delivered",Z66="Returned"),1,0) -> 0 | AJ66: =IF(Z66="Cancelled",1,0) -> 1 | AK66: =1 -> 1
A67: ORD-04134 | B67: 45628 | C67: 45628 | D67: CUST52437 | E67: Rohan Kapoor | F67: 24 | G67: 24 | H67: Female | I67: Female | J67: East | K67: Patna | L67: Furniture | M67: Wardrobe | N67: 5 | O67: 5 | P67: 14663.57 | Q67: 0.39 | R67: 43871.43 | S67: 8682.18 | T67: 0.198 | U67: 101.24 | V67: Credit Card | W67: 4 | X67: FALSE | Y67: Delivered | Z67: Delivered | AA67: 3 | AB67: 3 | AC67: 2024 | AD67: 45627 | AE67: 18-25 | AF67: 31-40% | AG67: =IF(N67=999,"Exclude","Include") -> Include | AH67: =IF(Z67="Returned",1,0) -> 0 | AI67: =IF(OR(Z67="Delivered",Z67="Returned"),1,0) -> 1 | AJ67: =IF(Z67="Cancelled",1,0) -> 0 | AK67: =1 -> 1
A68: ORD-04132 | B68: 45628 | C68: 45628 | D68: CUST70066 | E68: Ritu Rao | H68: Male | I68: Male | J68: North | K68: Amritsar | L68: Groceries | M68: Dal (1kg) | P68: 64.93 | Q68: 0.31 | R68: 43.37 | S68: 2.91 | T68: 0.067 | U68: 55.14 | V68: Credit Card | W68: 4 | X68: FALSE | Y68: Shipped | Z68: Shipped | AA68: 3 | AB68: 3 | AC68: 2024 | AD68: 45627 | AE68: Unknown | AF68: 31-40% | AG68: =IF(N68=999,"Exclude","Include") -> Include | AH68: =IF(Z68="Returned",1,0) -> 0 | AI68: =IF(OR(Z68="Delivered",Z68="Returned"),1,0) -> 0 | AJ68: =IF(Z68="Cancelled",1,0) -> 0 | AK68: =1 -> 1
A69: ORD-04135 | B69: 45628 | C69: 45628 | D69: CUST23239 | E69: Vikram Mehta | F69: 53 | G69: 53 | H69: Male | I69: Male | J69: North | K69: Delhi | L69: Clothing | M69: Kurta | N69: 9 | O69: 9 | P69: 3206.85 | Q69: 0.36 | R69: 16832.81 | S69: 7356.75 | T69: 0.437 | U69: 78.4 | V69: EMI | W69: 2 | X69: FALSE | Y69: Delivered | Z69: Delivered | AA69: 9 | AB69: 9 | AC69: 2024 | AD69: 45627 | AE69: 46-60 | AF69: 31-40% | AG69: =IF(N69=999,"Exclude","Include") -> Include | AH69: =IF(Z69="Returned",1,0) -> 0 | AI69: =IF(OR(Z69="Delivered",Z69="Returned"),1,0) -> 1 | AJ69: =IF(Z69="Cancelled",1,0) -> 0 | AK69: =1 -> 1
A70: ORD-04133 | B70: 45628 | C70: 45628 | D70: CUST61673 | E70: Kavya Joshi | F70: 42 | G70: 42 | H70: Female | I70: Female | J70: Central | K70: Raipur | L70: Sports | M70: Tennis Racket | N70: 5 | O70: 5 | P70: 6804.29 | Q70: 0.19 | R70: 29844.9 | S70: 8007.3 | T70: 0.268 | U70: 38.07 | V70: EMI | W70: 5 | X70: FALSE | Y70: Delivered | Z70: Delivered | AA70: 6 | AB70: 6 | AC70: 2024 | AD70: 45627 | AE70: 36-45 | AF70: 11-20% | AG70: =IF(N70=999,"Exclude","Include") -> Include | AH70: =IF(Z70="Returned",1,0) -> 0 | AI70: =IF(OR(Z70="Delivered",Z70="Returned"),1,0) -> 1 | AJ70: =IF(Z70="Cancelled",1,0) -> 0 | AK70: =1 -> 1
A71: ORD-04131 | B71: 45627 | C71: 45627 | D71: CUST27632 | E71: Pooja Kumar | F71: 24 | G71: 24 | H71: Female | I71: Female | J71: North | K71: Ludhiana | L71: Clothing | M71: Kurta | N71: 1 | O71: 1 | P71: 3420.38 | Q71: 0.01 | R71: 3473.11 | S71: 1562.14 | T71: 0.45 | U71: 63.61 | V71: Debit Card | X71: FALSE | Y71: Delivered | Z71: Delivered | AA71: 4 | AB71: 4 | AC71: 2024 | AD71: 45627 | AE71: 18-25 | AF71: 1-10% | AG71: =IF(N71=999,"Exclude","Include") -> Include | AH71: =IF(Z71="Returned",1,0) -> 0 | AI71: =IF(OR(Z71="Delivered",Z71="Returned"),1,0) -> 1 | AJ71: =IF(Z71="Cancelled",1,0) -> 0 | AK71: =1 -> 1
A72: ORD-04130 | B72: 45627 | C72: 45627 | D72: CUST33881 | E72: Priya Gupta | F72: 39 | G72: 39 | H72: male | I72: Male | J72: Central | K72: Indore | L72: Beauty | M72: Sunscreen | N72: 8 | O72: 8 | P72: 1289.19 | Q72: 0.15 | R72: 9301.95 | S72: 4080.67 | T72: 0.439 | U72: 43.57 | V72: EMI | W72: 1 | X72: FALSE | Y72: Cancelled | Z72: Cancelled | AA72: 2 | AB72: 2 | AC72: 2024 | AD72: 45627 | AE72: 36-45 | AF72: 11-20% | AG72: =IF(N72=999,"Exclude","Include") -> Include | AH72: =IF(Z72="Returned",1,0) -> 0 | AI72: =IF(OR(Z72="Delivered",Z72="Returned"),1,0) -> 0 | AJ72: =IF(Z72="Cancelled",1,0) -> 1 | AK72: =1 -> 1
A73: ORD-04126 | B73: 45626 | C73: 45626 | D73: CUST88649 | E73: Pooja Iyer | F73: 30 | G73: 30 | H73: Female | I73: Female | J73: South | K73: Chennai | L73: Books | M73: Self-Help Book | N73: 10 | O73: 10 | P73: 1308.63 | Q73: 0.39 | R73: 8038.79 | S73: 3691.88 | T73: 0.459 | U73: 59.74 | V73: EMI | W73: 5 | X73: FALSE | Y73: Delivered | Z73: Delivered | AA73: 9 | AB73: 9 | AC73: 2024 | AD73: 45597 | AE73: 26-35 | AF73: 31-40% | AG73: =IF(N73=999,"Exclude","Include") -> Include | AH73: =IF(Z73="Returned",1,0) -> 0 | AI73: =IF(OR(Z73="Delivered",Z73="Returned"),1,0) -> 1 | AJ73: =IF(Z73="Cancelled",1,0) -> 0 | AK73: =1 -> 1
A74: ORD-04128 | B74: 45626 | C74: 45626 | D74: CUST77827 | E74: Shreya Iyer | F74: 50 | G74: 50 | H74: Female | I74: Female | J74: West | K74: Surat | L74: Sports | M74: Cricket Bat | N74: 1 | O74: 1 | P74: 3657.04 | R74: 3446.01 | S74: 616.93 | T74: 0.179 | U74: 48.37 | V74: Debit Card | W74: 3 | X74: FALSE | Y74: Delivered | Z74: Delivered | AA74: 1 | AB74: 1 | AC74: 2024 | AD74: 45597 | AE74: 46-60 | AF74: No data | AG74: =IF(N74=999,"Exclude","Include") -> Include | AH74: =IF(Z74="Returned",1,0) -> 0 | AI74: =IF(OR(Z74="Delivered",Z74="Returned"),1,0) -> 1 | AJ74: =IF(Z74="Cancelled",1,0) -> 0 | AK74: =1 -> 1
A75: ORD-04129 | B75: 45626 | C75: 45626 | D75: CUST74208 | E75: Kavya Bose | F75: 12 | G75: 12 | H75: Male | I75: Male | J75: North | K75: Delhi | L75: Electronics | M75: Laptop | N75: 2 | O75: 2 | P75: 20309.39 | Q75: 0.15 | R75: 30407.42 | S75: 3438.98 | T75: 0.113 | U75: 38.43 | V75: Debit Card | W75: 2 | X75: FALSE | Y75: Delivered | Z75: Delivered | AA75: 4 | AB75: 4 | AC75: 2024 | AD75: 45597 | AE75: <18 | AF75: 11-20% | AG75: =IF(N75=999,"Exclude","Include") -> Include | AH75: =IF(Z75="Returned",1,0) -> 0 | AI75: =IF(OR(Z75="Delivered",Z75="Returned"),1,0) -> 1 | AJ75: =IF(Z75="Cancelled",1,0) -> 0 | AK75: =1 -> 1
A76: ORD-04127 | B76: 45626 | C76: 45626 | D76: CUST07792 | E76: Priya Joshi | F76: 34 | G76: 34 | H76: Male | I76: Male | J76: West | K76: Surat | L76: Beauty | M76: Lipstick | N76: 4 | O76: 4 | P76: 1854.35 | Q76: 0.04 | R76: 6462.23 | S76: 3552.01 | T76: 0.55 | U76: 32.77 | V76: Net Banking | W76: 5 | X76: FALSE | Y76: Delivered | Z76: Delivered | AA76: 2 | AB76: 2 | AC76: 2024 | AD76: 45597 | AE76: 26-35 | AF76: 1-10% | AG76: =IF(N76=999,"Exclude","Include") -> Include | AH76: =IF(Z76="Returned",1,0) -> 0 | AI76: =IF(OR(Z76="Delivered",Z76="Returned"),1,0) -> 1 | AJ76: =IF(Z76="Cancelled",1,0) -> 0 | AK76: =1 -> 1
A77: ORD-04125 | B77: 45625 | C77: 45625 | D77: CUST69485 | E77: Pooja Verma | F77: 15 | G77: 15 | H77: m | I77: Male | J77: East | K77: Kolkata | L77: Electronics | M77: Tablet | N77: 5 | O77: 5 | P77: 60589.34 | Q77: 0 | R77: 289044.77 | S77: 32628.88 | T77: 0.113 | U77: 117.75 | V77: Cash on Delivery | W77: 1 | X77: FALSE | Y77: Delivered | Z77: Delivered | AA77: 6 | AB77: 6 | AC77: 2024 | AD77: 45597 | AE77: <18 | AF77: 0 | AG77: =IF(N77=999,"Exclude","Include") -> Include | AH77: =IF(Z77="Returned",1,0) -> 0 | AI77: =IF(OR(Z77="Delivered",Z77="Returned"),1,0) -> 1 | AJ77: =IF(Z77="Cancelled",1,0) -> 0 | AK77: =1 -> 1
A78: ORD-04124 | B78: 45625 | C78: 45625 | D78: CUST93821 | E78: Rahul Mehta | F78: 57 | G78: 57 | H78: Other | I78: Other | J78: South | K78: Hyderabad | L78: Clothing | M78: Saree | N78: 7 | O78: 7 | P78: 2979.19 | Q78: 0.27 | R78: 16150.97 | S78: 6112.46 | T78: 0.378 | U78: 84.04 | V78: Cash on Delivery | W78: 1 | X78: FALSE | Y78: Delivered | Z78: Delivered | AA78: 7 | AB78: 7 | AC78: 2024 | AD78: 45597 | AE78: 46-60 | AF78: 21-30% | AG78: =IF(N78=999,"Exclude","Include") -> Include | AH78: =IF(Z78="Returned",1,0) -> 0 | AI78: =IF(OR(Z78="Delivered",Z78="Returned"),1,0) -> 1 | AJ78: =IF(Z78="Cancelled",1,0) -> 0 | AK78: =1 -> 1
A79: ORD-04123 | B79: 45624 | C79: 45624 | D79: CUST56868 | E79: Ananya Pillai | F79: 17 | G79: 17 | H79: Other | I79: Other | J79: East | K79: Patna | L79: Books | M79: Comic Book | N79: 9 | O79: 9 | P79: 1408.86 | Q79: 0.16 | R79: 10070.83 | S79: 3795.39 | T79: 0.377 | U79: 79.06 | V79: EMI | W79: 4 | X79: FALSE | Y79: Delivered | Z79: Delivered | AA79: 2 | AB79: 2 | AC79: 2024 | AD79: 45597 | AE79: <18 | AF79: 11-20% | AG79: =IF(N79=999,"Exclude","Include") -> Include | AH79: =IF(Z79="Returned",1,0) -> 0 | AI79: =IF(OR(Z79="Delivered",Z79="Returned"),1,0) -> 1 | AJ79: =IF(Z79="Cancelled",1,0) -> 0 | AK79: =1 -> 1
A80: ORD-04121 | B80: 45623 | C80: 45623 | D80: CUST46430 | E80: Arjun Iyer | F80: 42 | G80: 42 | H80: Male | I80: Male | J80: East | K80: Guwahati | L80: Electronics | M80: Laptop | N80: 7 | O80: 7 | P80: 26719.46 | Q80: 0.32 | R80: 125839.81 | S80: 16743.79 | T80: 0.133 | U80: 87.4 | V80: Credit Card | W80: 1 | X80: FALSE | Y80: Delivered | Z80: Delivered | AA80: 9 | AB80: 9 | AC80: 2024 | AD80: 45597 | AE80: 36-45 | AF80: 31-40% | AG80: =IF(N80=999,"Exclude","Include") -> Include | AH80: =IF(Z80="Returned",1,0) -> 0 | AI80: =IF(OR(Z80="Delivered",Z80="Returned"),1,0) -> 1 | AJ80: =IF(Z80="Cancelled",1,0) -> 0 | AK80: =1 -> 1
A81: ORD-04122 | B81: 45623 | C81: 45623 | D81: CUST89767 | E81: Rahul Patel | F81: 21 | G81: 21 | H81: Other | I81: Other | J81: South | K81: Kochi | L81: Electronics | M81: Camera | N81: 10 | O81: 10 | P81: 78416.65 | Q81: 0.19 | R81: 598247.4 | S81: 76981.5 | T81: 0.129 | U81: 47.97 | V81: UPI | W81: 3 | X81: FALSE | Y81: Cancelled | Z81: Cancelled | AA81: 8 | AB81: 8 | AC81: 2024 | AD81: 45597 | AE81: 18-25 | AF81: 11-20% | AG81: =IF(N81=999,"Exclude","Include") -> Include | AH81: =IF(Z81="Returned",1,0) -> 0 | AI81: =IF(OR(Z81="Delivered",Z81="Returned"),1,0) -> 0 | AJ81: =IF(Z81="Cancelled",1,0) -> 1 | AK81: =1 -> 1
A82: ORD-04120 | B82: 45623 | C82: 45623 | D82: CUST60757 | E82: Deepa Singh | F82: 20 | G82: 20 | H82: f | I82: Female | J82: South | K82: Bangalore | L82: Clothing | M82: Dress | N82: 1 | O82: 1 | P82: 335.42 | Q82: 0.23 | R82: 247.75 | S82: 88.1 | T82: 0.356 | U82: 73.88 | V82: Debit Card | W82: 3 | X82: FALSE | Y82: Delivered | Z82: Delivered | AA82: 3 | AB82: 3 | AC82: 2024 | AD82: 45597 | AE82: 18-25 | AF82: 21-30% | AG82: =IF(N82=999,"Exclude","Include") -> Include | AH82: =IF(Z82="Returned",1,0) -> 0 | AI82: =IF(OR(Z82="Delivered",Z82="Returned"),1,0) -> 1 | AJ82: =IF(Z82="Cancelled",1,0) -> 0 | AK82: =1 -> 1
A83: ORD-04119 | B83: 45623 | C83: 45623 | D83: CUST78271 | E83: Rahul Reddy | F83: 14 | G83: 14 | H83: Female | I83: Female | J83: East | K83: Guwahati | L83: Clothing | M83: Saree | N83: 8 | O83: 8 | P83: 612.16 | Q83: 0.05 | R83: 4471.04 | S83: 845.36 | T83: 0.189 | U83: 119.57 | V83: UPI | W83: 2 | X83: FALSE | Y83: Delivered | Z83: Delivered | AC83: 2024 | AD83: 45597 | AE83: <18 | AF83: 1-10% | AG83: =IF(N83=999,"Exclude","Include") -> Include | AH83: =IF(Z83="Returned",1,0) -> 0 | AI83: =IF(OR(Z83="Delivered",Z83="Returned"),1,0) -> 1 | AJ83: =IF(Z83="Cancelled",1,0) -> 0 | AK83: =1 -> 1
A84: ORD-04116 | B84: 45622 | C84: 45622 | D84: CUST40250 | E84: Karan Joshi | F84: 42 | G84: 42 | H84: Female | I84: Female | J84: Central | K84: Indore | L84: Beauty | M84: Lipstick | N84: 4 | O84: 4 | P84: 2248.41 | Q84: 0.29 | R84: 6511.18 | S84: 3980.78 | T84: 0.611 | U84: 20.27 | V84: EMI | W84: 3 | X84: FALSE | Y84: Cancelled | Z84: Cancelled | AA84: 1 | AB84: 1 | AC84: 2024 | AD84: 45597 | AE84: 36-45 | AF84: 21-30% | AG84: =IF(N84=999,"Exclude","Include") -> Include | AH84: =IF(Z84="Returned",1,0) -> 0 | AI84: =IF(OR(Z84="Delivered",Z84="Returned"),1,0) -> 0 | AJ84: =IF(Z84="Cancelled",1,0) -> 1 | AK84: =1 -> 1
A85: ORD-04117 | B85: 45622 | C85: 45622 | D85: CUST68421 | E85: Karan Reddy | F85: 43 | G85: 43 | H85: female | I85: Female | J85: North | K85: Chandigarh | L85: Beauty | M85: Shampoo | N85: 9 | O85: 9 | P85: 328.65 | Q85: 0.3 | R85: 1975.97 | S85: 543.25 | T85: 0.275 | U85: 41.68 | V85: Credit Card | W85: 4 | X85: FALSE | Y85: delivered | Z85: Delivered | AA85: 9 | AB85: 9 | AC85: 2024 | AD85: 45597 | AE85: 36-45 | AF85: 21-30% | AG85: =IF(N85=999,"Exclude","Include") -> Include | AH85: =IF(Z85="Returned",1,0) -> 0 | AI85: =IF(OR(Z85="Delivered",Z85="Returned"),1,0) -> 1 | AJ85: =IF(Z85="Cancelled",1,0) -> 0 | AK85: =1 -> 1
A86: ORD-04118 | B86: 45622 | C86: 45622 | D86: CUST48264 | E86: Aarav Chatterjee | F86: 56 | G86: 56 | H86: Other | I86: Other | J86: North | K86: Amritsar | L86: Clothing | M86: Saree | N86: 9 | O86: 9 | P86: 2252.16 | Q86: 0.09 | R86: 17908.2 | S86: 4417.35 | T86: 0.247 | U86: 42.65 | V86: Net Banking | W86: 5 | X86: FALSE | Y86: Shipped | Z86: Shipped | AA86: 5 | AB86: 5 | AC86: 2024 | AD86: 45597 | AE86: 46-60 | AF86: 1-10% | AG86: =IF(N86=999,"Exclude","Include") -> Include | AH86: =IF(Z86="Returned",1,0) -> 0 | AI86: =IF(OR(Z86="Delivered",Z86="Returned"),1,0) -> 0 | AJ86: =IF(Z86="Cancelled",1,0) -> 0 | AK86: =1 -> 1
A87: ORD-04115 | B87: 45621 | C87: 45621 | D87: CUST88970 | E87: Ritu Pillai | F87: 38 | G87: 38 | H87: Other | I87: Other | J87: East | K87: Patna | L87: Electronics | M87: Smartwatch | N87: 9 | O87: 9 | P87: 76064.53 | Q87: 0.25 | R87: 473255.79 | S87: 56343.87 | T87: 0.119 | U87: 79.71 | V87: Cash on Delivery | W87: 3 | X87: FALSE | Y87: Delivered | Z87: Delivered | AA87: 1 | AB87: 1 | AC87: 2024 | AD87: 45597 | AE87: 36-45 | AF87: 21-30% | AG87: =IF(N87=999,"Exclude","Include") -> Include | AH87: =IF(Z87="Returned",1,0) -> 0 | AI87: =IF(OR(Z87="Delivered",Z87="Returned"),1,0) -> 1 | AJ87: =IF(Z87="Cancelled",1,0) -> 0 | AK87: =1 -> 1
A88: ORD-04114 | B88: 45621 | C88: 45621 | D88: CUST90879 | E88: Aarav Pillai | F88: 38 | G88: 38 | H88: Other | I88: Other | J88: West | K88: Pune | L88: Clothing | M88: Jacket | N88: 8 | O88: 8 | P88: 2242.21 | Q88: 0.08 | R88: 15849.85 | S88: 5745.26 | T88: 0.362 | U88: 58.08 | V88: UPI | W88: 3 | X88: FALSE | Y88: cancelled | Z88: Cancelled | AA88: 5 | AB88: 5 | AC88: 2024 | AD88: 45597 | AE88: 36-45 | AF88: 1-10% | AG88: =IF(N88=999,"Exclude","Include") -> Include | AH88: =IF(Z88="Returned",1,0) -> 0 | AI88: =IF(OR(Z88="Delivered",Z88="Returned"),1,0) -> 0 | AJ88: =IF(Z88="Cancelled",1,0) -> 1 | AK88: =1 -> 1
A89: ORD-04111 | B89: November 22, 2024 | C89: 45618 | D89: CUST99588 | E89: Meera Kumar | F89: 57 | G89: 57 | H89: Female | I89: Female | J89: Central | K89: Indore | L89: Books | M89: Comic Book | N89: 7 | O89: 7 | P89: 785.67 | Q89: 0.12 | R89: 4582.79 | S89: 2037.5 | T89: 0.445 | U89: 63.64 | V89: Credit Card | W89: 3 | X89: FALSE | Y89: Delivered | Z89: Delivered | AA89: 2 | AB89: 2 | AC89: 2024 | AD89: 45597 | AE89: 46-60 | AF89: 11-20% | AG89: =IF(N89=999,"Exclude","Include") -> Include | AH89: =IF(Z89="Returned",1,0) -> 0 | AI89: =IF(OR(Z89="Delivered",Z89="Returned"),1,0) -> 1 | AJ89: =IF(Z89="Cancelled",1,0) -> 0 | AK89: =1 -> 1
A90: ORD-04112 | B90: 45618 | C90: 45618 | D90: CUST28483 | E90: Pooja Gupta | F90: 23 | G90: 23 | H90: Other | I90: Other | J90: Central | K90: Nagpur | L90: Clothing | M90: Jacket | N90: 8 | O90: 8 | P90: 3689.55 | Q90: 0.36 | R90: 22365.27 | S90: 6339.32 | T90: 0.283 | U90: 82.16 | V90: Debit Card | W90: 4 | X90: FALSE | Y90: Pending | Z90: Pending | AA90: 4 | AB90: 4 | AC90: 2024 | AD90: 45597 | AE90: 18-25 | AF90: 31-40% | AG90: =IF(N90=999,"Exclude","Include") -> Include | AH90: =IF(Z90="Returned",1,0) -> 0 | AI90: =IF(OR(Z90="Delivered",Z90="Returned"),1,0) -> 0 | AJ90: =IF(Z90="Cancelled",1,0) -> 0 | AK90: =1 -> 1
A91: ORD-04113 | B91: 45618 | C91: 45618 | D91: CUST10274 | E91: Arjun Gupta | F91: 13 | G91: 13 | H91: Other | I91: Other | J91: Central | K91: Bhopal | L91: Groceries | M91: Rice (5kg) | N91: 8 | O91: 8 | P91: 185.5 | Q91: 0.29 | R91: 1001.02 | S91: 79.89 | T91: 0.08 | U91: 48.43 | V91: Debit Card | W91: 5 | X91: FALSE | Y91: Pending | Z91: Pending | AA91: 6 | AB91: 6 | AC91: 2024 | AD91: 45597 | AE91: <18 | AF91: 21-30% | AG91: =IF(N91=999,"Exclude","Include") -> Include | AH91: =IF(Z91="Returned",1,0) -> 0 | AI91: =IF(OR(Z91="Delivered",Z91="Returned"),1,0) -> 0 | AJ91: =IF(Z91="Cancelled",1,0) -> 0 | AK91: =1 -> 1
A92: ORD-04109 | B92: 45616 | C92: 45616 | D92: CUST36614 | E92: Shreya Pillai | F92: 27 | G92: 27 | H92: Other | I92: Other | J92: East | K92: Guwahati | L92: Books | M92: Comic Book | N92: 9 | O92: 9 | P92: 1324.57 | Q92: 0.38 | R92: 7683.45 | S92: 2086.59 | T92: 0.272 | U92: 82.14 | V92: UPI | W92: 4 | X92: FALSE | Y92: Delivered | Z92: Delivered | AA92: 4 | AB92: 4 | AC92: 2024 | AD92: 45597 | AE92: 26-35 | AF92: 31-40% | AG92: =IF(N92=999,"Exclude","Include") -> Include | AH92: =IF(Z92="Returned",1,0) -> 0 | AI92: =IF(OR(Z92="Delivered",Z92="Returned"),1,0) -> 1 | AJ92: =IF(Z92="Cancelled",1,0) -> 0 | AK92: =1 -> 1
A93: ORD-04110 | B93: 45616 | C93: 45616 | D93: CUST48614 | E93: Sanjay Bose | F93: 31 | G93: 31 | H93: Female | I93: Female | J93: South | K93: Bangalore | L93: Groceries | M93: Tea | N93: 1 | O93: 1 | P93: 281.65 | Q93: 0.11 | R93: 268.27 | S93: 27.01 | T93: 0.101 | U93: 73.96 | V93: UPI | W93: 1 | X93: TRUE | Y93: Returned | Z93: Returned | AA93: 7 | AB93: 7 | AC93: 2024 | AD93: 45597 | AE93: 26-35 | AF93: 11-20% | AG93: =IF(N93=999,"Exclude","Include") -> Include | AH93: =IF(Z93="Returned",1,0) -> 1 | AI93: =IF(OR(Z93="Delivered",Z93="Returned"),1,0) -> 1 | AJ93: =IF(Z93="Cancelled",1,0) -> 0 | AK93: =1 -> 1
A94: ORD-04106 | B94: 45614 | C94: 45614 | D94: CUST44096 | E94: Karan Mehta | F94: 24 | G94: 24 | H94: Male | I94: Male | J94: West | K94: Ahmedabad | L94: Clothing | M94: Saree | N94: 6 | O94: 6 | P94: 3683.81 | Q94: 0.14 | R94: 18294.23 | S94: 6945.87 | T94: 0.38 | U94: 62.15 | V94: Credit Card | W94: 3 | X94: FALSE | Y94: Delivered | Z94: Delivered | AA94: 7 | AB94: 7 | AC94: 2024 | AD94: 45597 | AE94: 18-25 | AF94: 11-20% | AG94: =IF(N94=999,"Exclude","Include") -> Include | AH94: =IF(Z94="Returned",1,0) -> 0 | AI94: =IF(OR(Z94="Delivered",Z94="Returned"),1,0) -> 1 | AJ94: =IF(Z94="Cancelled",1,0) -> 0 | AK94: =1 -> 1
A95: ORD-04108 | B95: 45614 | C95: 45614 | D95: CUST02996 | E95: Sunita Mehta | F95: 42 | G95: 42 | H95: Male | I95: Male | J95: South | K95: Chennai | L95: Clothing | M95: Jacket | N95: -1 | P95: 3079.53 | Q95: 0.11 | R95: 2711.38 | S95: 987.61 | T95: 0.364 | U95: 68.17 | V95: Credit Card | W95: 5 | X95: FALSE | Y95: Cancelled | Z95: Cancelled | AA95: 1 | AB95: 1 | AC95: 2024 | AD95: 45597 | AE95: 36-45 | AF95: 11-20% | AG95: =IF(N95=999,"Exclude","Include") -> Include | AH95: =IF(Z95="Returned",1,0) -> 0 | AI95: =IF(OR(Z95="Delivered",Z95="Returned"),1,0) -> 0 | AJ95: =IF(Z95="Cancelled",1,0) -> 1 | AK95: =1 -> 1
A96: ORD-04107 | B96: 45614 | C96: 45614 | D96: CUST81738 | E96: Meera Verma | F96: 57 | G96: 57 | H96: Female | I96: Female | J96: North | K96: Ludhiana | L96: Sports | M96: Cycle | N96: 6 | O96: 6 | P96: 8448.34 | Q96: 0.29 | R96: 37263.52 | S96: 8591.2 | T96: 0.231 | U96: 72.43 | V96: Cash on Delivery | W96: 5 | X96: FALSE | Y96: Delivered | Z96: Delivered | AA96: 10 | AB96: 10 | AC96: 2024 | AD96: 45597 | AE96: 46-60 | AF96: 21-30% | AG96: =IF(N96=999,"Exclude","Include") -> Include | AH96: =IF(Z96="Returned",1,0) -> 0 | AI96: =IF(OR(Z96="Delivered",Z96="Returned"),1,0) -> 1 | AJ96: =IF(Z96="Cancelled",1,0) -> 0 | AK96: =1 -> 1
A97: ORD-04104 | B97: 45613 | C97: 45613 | D97: CUST00610 | E97: Priya Verma | F97: 14 | G97: 14 | H97: Male | I97: Male | J97: North | K97: Amritsar | L97: Clothing | M97: Jacket | N97: 8 | O97: 8 | P97: 1693.73 | Q97: 0.03 | R97: 12090.22 | S97: 3498.38 | T97: 0.289 | U97: 36.04 | V97: Credit Card | X97: FALSE | Y97: Cancelled | Z97: Cancelled | AA97: 5 | AB97: 5 | AC97: 2024 | AD97: 45597 | AE97: <18 | AF97: 1-10% | AG97: =IF(N97=999,"Exclude","Include") -> Include | AH97: =IF(Z97="Returned",1,0) -> 0 | AI97: =IF(OR(Z97="Delivered",Z97="Returned"),1,0) -> 0 | AJ97: =IF(Z97="Cancelled",1,0) -> 1 | AK97: =1 -> 1
A98: ORD-04105 | B98: 45613 | C98: 45613 | D98: CUST23063 | E98: Rohan Rao | F98: 33 | G98: 33 | H98: Other | I98: Other | J98: East | K98: Patna | L98: Sports | M98: Tennis Racket | N98: 8 | O98: 8 | P98: 10030.91 | Q98: 0.02 | R98: 67222.6 | S98: 15466.13 | T98: 0.23 | U98: 100.02 | V98: EMI | W98: 3 | X98: FALSE | Y98: Delivered | Z98: Delivered | AA98: 3 | AB98: 3 | AC98: 2024 | AD98: 45597 | AE98: 26-35 | AF98: 1-10% | AG98: =IF(N98=999,"Exclude","Include") -> Include | AH98: =IF(Z98="Returned",1,0) -> 0 | AI98: =IF(OR(Z98="Delivered",Z98="Returned"),1,0) -> 1 | AJ98: =IF(Z98="Cancelled",1,0) -> 0 | AK98: =1 -> 1
A99: ORD-04101 | B99: 45612 | C99: 45612 | D99: CUST53114 | E99: Kavya Bose | F99: 35 | G99: 35 | H99: Female | I99: Female | J99: West | K99: Pune | L99: Electronics | M99: Headphones | N99: 3 | O99: 3 | P99: 36271.47 | Q99: 0.08 | R99: 106383.22 | S99: 8562.92 | T99: 0.08 | U99: 64.31 | V99: Credit Card | W99: 2 | X99: TRUE | Y99: Returned | Z99: Returned | AA99: 10 | AB99: 10 | AC99: 2024 | AD99: 45597 | AE99: 26-35 | AF99: 1-10% | AG99: =IF(N99=999,"Exclude","Include") -> Include | AH99: =IF(Z99="Returned",1,0) -> 1 | AI99: =IF(OR(Z99="Delivered",Z99="Returned"),1,0) -> 1 | AJ99: =IF(Z99="Cancelled",1,0) -> 0 | AK99: =1 -> 1
A100: ORD-04103 | B100: 45612 | C100: 45612 | D100: CUST86891 | E100: Sanjay Mehta | F100: 53 | G100: 53 | H100: female | I100: Female | J100: North | K100: Delhi | L100: Sports | M100: Tennis Racket | N100: 6 | O100: 6 | P100: 6418.63 | Q100: 0.12 | R100: 31683.87 | S100: 6743.34 | T100: 0.213 | U100: 60.52 | V100: Credit Card | W100: 3 | X100: FALSE | Y100: Delivered | Z100: Delivered | AA100: 5 | AB100: 5 | AC100: 2024 | AD100: 45597 | AE100: 46-60 | AF100: 11-20% | AG100: =IF(N100=999,"Exclude","Include") -> Include | AH100: =IF(Z100="Returned",1,0) -> 0 | AI100: =IF(OR(Z100="Delivered",Z100="Returned"),1,0) -> 1 | AJ100: =IF(Z100="Cancelled",1,0) -> 0 | AK100: =1 -> 1
...

Sheet Per Tahun
A1: order_status_clean | B1: Delivered
A2: sales_flag | B2: Include
A4: Row Labels | B4: Sum of sales_amount | C4: Sum of profit
A5: 2020 | B5: 24493418 | C5: 4582796.9
A6: 2021 | B6: 29858426 | C6: 5408425.1
A7: 2022 | B7: 32976549 | C7: 6295256.3
A8: 2023 | B8: 32599571 | C8: 5960575.6
A9: 2024 | B9: 33587242 | C9: 6462756.1
A10: Grand Total | B10: 153515205 | C10: 28709810

Sheet Bulanan
A1: order_status_clean | B1: Delivered
A2: sales_flag | B2: Include
A4: Row Labels | B4: Sum of sales_amount
A5: 43831 | B5: 944705.47
A6: 43862 | B6: 1316719.4
A7: 43891 | B7: 1556181
A8: 43922 | B8: 1812229.5
A9: 43952 | B9: 4415841.7
A10: 43983 | B10: 2266182.7
A11: 44013 | B11: 3707588.1
A12: 44044 | B12: 1605204.2
A13: 44075 | B13: 1770257.8
A14: 44105 | B14: 2057622.4
A15: 44136 | B15: 987267.89
A16: 44166 | B16: 2053617.7
... A64: 45627 | B64: 2104057.4
A65: Grand Total | B65: 1.5351521e+08

Sheet Kategori
A1: order_status_clean | B1: Delivered
A2: sales_flag | B2: Include
A4: Row Labels | B4: Penjualan | C4: Margin %
A5: Electronics | B5: 88979113 | C5: 0.11937182
A6: Furniture | B6: 39662721 | C6: 0.28373867
A7: Sports | B7: 16076064 | C7: 0.22066753
A8: Clothing | B8: 4252225.8 | C8: 0.35501945
A9: Beauty | B9: 2551914.5 | C9: 0.44966841
A10: Books | B10: 1476232.2 | C10: 0.39900197
A11: Groceries | B11: 516935.54 | C11: 0.078811335
A12: Grand Total | B12: 1.535152e+08 | C12: 0.18701607

Sheet Kategori x Tahun
A1: order_status_clean | B1: Delivered
A2: sales_flag | B2: Include
A4: Sum of sales_amount | B4: Column Labels
A5: Row Labels | B5: 2020 | C5: 2021 | D5: 2022 | E5: 2023 | F5: 2024 | G5: Grand Total
A6: Beauty | B6: 440853.68 | C6: 446379.01 | D6: 506039.04 | E6: 543789.31 | F6: 614853.48 | G6: 2551914.5
A7: Books | B7: 241989.7 | C7: 287227.9 | D7: 274654.03 | E7: 327406.2 | F7: 344954.42 | G7: 1476232.2
A8: Clothing | B8: 585207.35 | C8: 828007.12 | D8: 899934.98 | E8: 934709.56 | F8: 1004366.8 | G8: 4252225.8
A9: Electronics | B9: 13708200 | C9: 18349261 | D9: 18407416 | E9: 19158618 | F9: 19355617 | G9: 88979113
A10: Furniture | B10: 6133848.8 | C10: 6323745 | D10: 9627694.3 | E10: 7703882.3 | F10: 9873550.1 | G10: 39662721
A11: Groceries | B11: 95456.37 | C11: 91095.93 | D11: 108438.54 | E11: 102897.8 | F11: 119046.9 | G11: 516935.54
A12: Sports | B12: 3287861.6 | C12: 3532709.5 | D12: 3152372.1 | E12: 3828267.4 | F12: 2274853.2 | G12: 16076064
A13: Grand Total | B13: 24493418 | C13: 29858426 | D13: 32976549 | E13: 32599571 | F13: 33587242 | G13: 153515205

Sheet Sports
A1: product_category | B1: Sports
A2: order_status_clean | B2: Delivered
A3: sales_flag | B3: Include
A5: Row Labels | B5: Count of order_id | C5: Sum of sales_amount | D5: Average of sales_amount2
A6: 2020 | B6: 85 | C6: 3287861.6 | D6: 38680.725
A7: 2021 | B7: 84 | C7: 3532709.5 | D7: 42056.066
A8: 2022 | B8: 84 | C8: 3152372.1 | D8: 37528.24
A9: 2023 | B9: 91 | C9: 3828267.4 | D9: 42068.872
A10: 2024 | B10: 68 | C10: 2274853.2 | D10: 33453.724
A11: Grand Total | B11: 412 | C11: 16076064 | D11: 39019.572

Sheet Penjualan Per Tahun (Sports)
A1: order_status_clean | B1: Delivered
A2: product_category | B2: Sports
A3: sales_flag | B3: Include
A5: Sum of sales_amount | B5: Column Labels
A6: Row Labels | B6: 2020 | C6: 2021 | D6: 2022 | E6: 2023 | F6: 2024 | G6: Grand Total
A7: Cricket Bat | B7: 420738.08 | C7: 1068777.2 | D7: 552583.9 | E7: 306592.45 | F7: 433244.51 | G7: 2781936.1
A8: Cycle | B8: 497335.69 | C8: 461825.95 | D8: 244610.9 | E8: 340657.82 | F8: 189121.44 | G8: 1733551.8
A9: Dumbbells | B9: 550713.17 | C9: 335167.35 | D9: 564971.2 | E9: 1209187.6 | F9: 557920.86 | G9: 3217960.2
A10: Football | B10: 721875.42 | C10: 642420.2 | D10: 650884.07 | E10: 569824.86 | F10: 339225.46 | G10: 2924230
A11: Tennis Racket | B11: 313153.39 | C11: 461901.48 | D11: 596331.45 | E11: 494079.59 | F11: 274844.05 | G11: 2140310
A12: Yoga Mat | B12: 784045.84 | C12: 562617.39 | D12: 542990.61 | E12: 907925.03 | F12: 480496.92 | G12: 3278075.8
A13: Grand Total | B13: 3287861.6 | C13: 3532709.5 | D13: 3152372.1 | E13: 3828267.4 | F13: 2274853.2 | G13: 16076064

Sheet Diskon
A1: order_status_clean | B1: Delivered
A2: sales_flag | B2: Include
A4: Row Labels | B4: Count of order_id | C4: Sum of sales_amount | D4: Sum of profit | E4: Sum of Margin
A5: 0 | B5: 29 | C5: 3449019.8 | D5: 544219.59 | E5: 0.15778964
A6: 1-10% | B6: 674 | C6: 39612856 | D6: 7450155.4 | E6: 0.18807418
A7: 11-20% | B7: 617 | C7: 38483846 | D7: 7139755.5 | E7: 0.18552604
A8: 21-30% | B8: 659 | C8: 37652690 | D8: 7073482.8 | E8: 0.18786129
A9: 31-40% | B9: 652 | C9: 27540735 | D9: 5071165.9 | E9: 0.18413328
A10: No data | B10: 94 | C10: 6776058.8 | D10: 1431030.8 | E10: 0.21118925
A11: Grand Total | B11: 2725 | C11: 1.5351521e+08 | D11: 28709810 | E11: 0.18701607

Sheet Payment
A1: order_status_clean | B1: Delivered | D1: Payment Methods
A2: sales_flag | B2: Include
A4: Row Labels | B4: Count of order_id
A5: UPI | B5: 496
A6: Credit Card | B6: 467
A7: Cash on Delivery | B7: 451
A8: EMI | B8: 440
A9: Net Banking | B9: 439
A10: Debit Card | B10: 432
A11: Grand Total | B11: 2725

Sheet Top 10
A1: order_status_clean | B1: Delivered
A2: sales_flag | B2: Include
A4: Row Labels | B4: Count of order_id | C4: Sum of sales_amount | D4: Sum of profit | E4: Sum of Margin
A5: Headphones | B5: 75 | C5: 19079423 | D5: 2252649.9 | E5: 0.11806698
A6: Desk | B6: 72 | C6: 7843971.1 | D6: 2185118.7 | E6: 0.27857302
A7: Wardrobe | B7: 64 | C7: 6976125.5 | D7: 2050081.6 | E7: 0.29387109
A8: Laptop | B8: 69 | C8: 17104668 | D8: 1974650.5 | E8: 0.11544513
A9: Sofa | B9: 58 | C9: 6504023.4 | D9: 1931222.1 | E9: 0.2969273
A10: Smartwatch | B10: 65 | C10: 15125842 | D10: 1826935.4 | E10: 0.1207824
A11: Bed Frame | B11: 69 | C11: 6468219.7 | D11: 1809008.1 | E11: 0.27967635
A12: Chair | B12: 59 | C12: 6047917.9 | D12: 1703254.8 | E12: 0.28162664
A13: Camera | B13: 58 | C13: 13998888 | D13: 1640238.2 | E13: 0.11716918
A14: Bookshelf | B14: 64 | C14: 5822463 | D14: 1575162.4 | E14: 0.27053197
A15: Grand Total | B15: 653 | C15: 1.0497154e+08 | D15: 18948322 | E15: 0.18050913

Sheet Bottom 10
A1: order_status_clean | B1: Delivered
A2: sales_flag | B2: Include
A4: Row Labels | B4: Count of order_id | C4: Sum of sales_amount | D4: Sum of profit | E4: Sum of Margin
A5: Rice (5kg) | B5: 63 | C5: 76391.66 | D5: 5784.38 | E5: 0.075720046
A6: Dal (1kg) | B6: 67 | C6: 80765.21 | D6: 6224.34 | E6: 0.077067094
A7: Flour | B7: 61 | C7: 82661.48 | D7: 6477.89 | E7: 0.078366489
A8: Sugar | B8: 58 | C8: 83734.58 | D8: 6642.41 | E8: 0.079326964
A9: Cooking Oil | B9: 64 | C9: 94444.78 | D9: 7330.65 | E9: 0.077618371
A10: Tea | B10: 62 | C10: 98937.83 | D10: 8280.71 | E10: 0.083696095
A11: Cook Book | B11: 52 | C11: 199473.52 | D11: 80105.75 | E11: 0.40158588
A12: Self-Help Book | B12: 62 | C12: 217934.28 | D12: 84257.72 | E12: 0.38661986
A13: Biography | B13: 52 | C13: 225604.18 | D13: 88710.24 | E13: 0.39321186
A14: Fiction Novel | B14: 76 | C14: 243865.5 | D14: 97151.44 | E14: 0.39838124
A15: Grand Total | B15: 617 | C15: 1403813 | D15: 390965.53 | E15: 0.27850257

Sheet Pivot Cancellation
A3: Row Labels | B3: Sum of cancelled | C3: Sum of orders_count | D3: Sum of Cancel Rate
A4: Cash on Delivery | B4: 55 | C4: 703 | D4: 0.078236131
A5: Credit Card | B5: 56 | C5: 721 | D5: 0.077669903
A6: Debit Card | B6: 69 | C6: 683 | D6: 0.10102489
A7: EMI | B7: 56 | C7: 683 | D7: 0.081991215
A8: Net Banking | B8: 52 | C8: 661 | D8: 0.078668684
A9: UPI | B9: 58 | C9: 749 | D9: 0.077436582
A10: (blank) | D10: #DIV/0!
A11: Grand Total | B11: 346 | C11: 4200 | D11: 0.082380952

Sheet Segmen
A1: order_status_clean | B1: Delivered
A2: sales_flag | B2: Include
A4: Row Labels | B4: Count of order_id | C4: Sum of sales_amount | D4: Sum of profit | E4: Sum of margin
A5: <18 | B5: 208 | C5: 12211811 | D5: 2145532 | E5: 0.17569319
A6: 18-25 | B6: 404 | C6: 26708147 | D6: 4727245.4 | E6: 0.17699638
A7: 26-35 | B7: 809 | C7: 42665646 | D7: 8085836.4 | E7: 0.18951633
A8: 36-45 | B8: 722 | C8: 41003329 | D8: 7842620.4 | E8: 0.19126789
A9: 46-60 | B9: 450 | C9: 23439151 | D9: 4647348.3 | E9: 0.19827289
A10: 60+ | B10: 36 | C10: 1322369.9 | D10: 258425.77 | E10: 0.19542623
A11: Unknown | B11: 96 | C11: 6164750.6 | D11: 1002801.8 | E11: 0.16266704
A12: Grand Total | B12: 2725 | C12: 1.5351521e+08 | D12: 28709810 | E12: 0.18701607

Sheet Pivot Kepuasan
A1: order_status_clean | B1: Delivered
A3: Row Labels | B3: Rata-rata Kepuasan | C3: Jumlah Rating
A4: 1 | B4: 3.246696 | C4: 227
A5: 2 | B5: 3.2226721 | C5: 247
A6: 3 | B6: 2.9918033 | C6: 244
A7: 4 | B7: 3.0368852 | C7: 244
A8: 5 | B8: 3.1196581 | C8: 234
A9: 6 | B9: 3.1264822 | C9: 253
A10: 7 | B10: 3.2268908 | C10: 238
A11: 8 | B11: 3.0269231 | C11: 260
A12: 9 | B12: 3.2669323 | C12: 251
A13: 10 | B13: 3.0083333 | C13: 240
A14: (blank) | B14: 3.2923077 | C14: 65
A15: Grand Total | B15: 3.1306432 | C15: 2503

Sheet KPI
A1: order_status_clean | B1: Delivered
A2: sales_flag | B2: Include
A4: Jumlah Order | B4: Total Penjualan | C4: Total Profit | D4: Rata-rata Per Order | E4: Sum of margin | F4: Rata-Rata Kepuasan | G4: Count of order_id
A5: 2725 | B5: 1.5351521e+08 | C5: 28709810 | D5: 56335.855 | E5: 0.18701607 | F5: 3.1301041 | G5: 2725

Sheet Sheet6
A1: order_status_clean | B1: Delivered
A2: sales_flag | B2: Include
A4: Row Labels | B4: Penjualan | C4: Sum of profit | D4: Sum of Margin
A5: Beauty | B5: 2551914.5 | C5: 1147515.4 | D5: 0.44966841
A6: Books | B6: 1476232.2 | C6: 589019.58 | D6: 0.39900197
A7: Clothing | B7: 4252225.8 | C7: 1509622.9 | D7: 0.35501945
A8: Electronics | B8: 88979113 | C8: 10621599 | D8: 0.11937182
A9: Furniture | B9: 39662721 | C9: 11253848 | D9: 0.28373867
A10: Groceries | B10: 516935.54 | C10: 40740.38 | D10: 0.078811335
A11: Sports | B11: 16076064 | C11: 3547465.3 | D11: 0.22066753
A12: Grand Total | B12: 1.535152e+08 | C12: 28709810 | D12: 0.18701607

Sheet Dashboard
G7: Total Penjualan | I7: Total Profit | K7: Margin | M7: Jumlah Order | O7: Rata-Rata Per Oder
G8: =GETPIVOTDATA("Total Penjualan",KPI!$A$4) -> 1.5351521e+08 | I8: =GETPIVOTDATA("Total Profit",KPI!$A$4) -> 28709810 | K8: =GETPIVOTDATA("Sum of margin",KPI!$A$4) -> 0.18701607 | M8: =GETPIVOTDATA("Jumlah Order",KPI!$A$4) -> 2725 | O8: =GETPIVOTDATA("Rata-rata Per Order",KPI!$A$4) -> 56335.855
